[
  {
    "title": "Fyrsti þáttur: Jens burstar aldrei tennurnar",
    "artist": "Leikhópurinn Karíus, Baktus",
    "isrc": "ISA111000202"
  },
  {
    "title": "Jakob og Tumi hittast",
    "artist": "Karl Ágúst Úlfsson",
    "isrc": "ISA220801583"
  },
  {
    "title": "Búkolla",
    "artist": "Ævar R. Kvaran",
    "isrc": "ISA110304201"
  },
  {
    "title": "Kalli flýgur um loftin blá",
    "artist": "Leikhópurinn Kalli á þakinu",
    "isrc": "ISA220900282"
  },
  {
    "title": "Tommi og Kamilla spjalla",
    "artist": "Leikhópurinn Kardemommubærinn",
    "isrc": "ISA111000105"
  },
  {
    "title": "Uppboðið í Bakkakoti",
    "artist": "Ýmsir leikarar",
    "isrc": "ISA109205902"
  },
  {
    "title": "Lína á Sjónarhóli",
    "artist": "Leikhópurinn Lína Langsokkur, Geirfuglarnir, Borgarleikhúsið",
    "isrc": "ISA220900167"
  },
  {
    "title": "Jósafar mannahrellir",
    "artist": "Leikhópurinn Benedikt búálfur",
    "isrc": "ISA110201074"
  },
  {
    "title": "Söngurinn um óskirnar",
    "artist": "Glámur og Skrámur",
    "isrc": "ISA109200601"
  },
  {
    "title": "Upphafskynning",
    "artist": "Guðjón Davíð Karlsson",
    "isrc": "ISA111201001"
  },
  {
    "title": "Fyrsti kafli",
    "artist": "Heiðdís Norðfjörð",
    "isrc": "ISA110707801"
  },
  {
    "title": "Strákurinn sem fauk út í veður og vind",
    "artist": "Anna Pálína, Aðalsteinn Ásberg",
    "isrc": "ISZ109800304"
  },
  {
    "title": "Mjallhvít",
    "artist": "Grimmsævintýrahópurinn",
    "isrc": "ISA110304601"
  },
  {
    "title": "Þrír litlir grísir",
    "artist": "Bessi Bjarnason",
    "isrc": "ISA110701604"
  },
  {
    "title": "Hér koma Smjattpattarnir (saga)",
    "artist": "Jóhann Sigurðarson",
    "isrc": "ISV442409502"
  },
  {
    "title": "Fótabað",
    "artist": "Sigurður Sigurjónsson",
    "isrc": "ISA110303609"
  },
  {
    "title": "úr Skjóðunni (1)",
    "artist": "Þorvaldur Þorsteinsson, Jóhann G. Jóhannsson",
    "isrc": "QZDA72078497"
  },
  {
    "title": "Fagur fiskur í sjó",
    "artist": "Skoppa og Skrítla",
    "isrc": "ISA110701902"
  },
  {
    "title": "Kötturinn og músin",
    "artist": "Kristjana Skúladóttir, Sögustund.is",
    "isrc": "ISV442010102"
  },
  {
    "title": "Rauðhetta",
    "artist": "Úr leikriti",
    "isrc": "ISA109602702"
  },
  {
    "title": "Krakkarnir í Kátugötu - bók 1",
    "artist": "Samgöngustofa",
    "isrc": "ISV442005801"
  },
  {
    "title": "Njósnarinn",
    "artist": "Sprotarnir",
    "isrc": "ISV441724801"
  },
  {
    "title": "Stafakarlinn K",
    "artist": "Bergljót Arnalds",
    "isrc": "ISA110807416"
  },
  {
    "title": "Fagur sumardagur",
    "artist": "Leikhópurinn Síglaðir söngvarar",
    "isrc": "ISA111000402"
  },
  {
    "title": "Ég syng um ost",
    "artist": "Leikhópurinn Gulleyjan",
    "isrc": "ISA111200409"
  },
  {
    "title": "Stígvélaði kötturinn",
    "artist": "Ýmsir leik, söngvarar",
    "isrc": "ISG220900044"
  },
  {
    "title": "Stúfur",
    "artist": "Árni Tryggvason",
    "isrc": "ISE109900303"
  },
  {
    "title": "Æfintýri í Mararþaraborg - 5",
    "artist": "Helgi Skúlason",
    "isrc": "ISA110303505"
  },
  {
    "title": "Í Kattholti",
    "artist": "Leikarar úr Emil í Kattholti",
    "isrc": "ISA109202202"
  },
  {
    "title": "Annar þáttur: Ég finn svo til í tönnunum",
    "artist": "Leikhópurinn Karíus, Baktus",
    "isrc": "ISA111000204"
  },
  {
    "title": "Tumi kynntur",
    "artist": "Karl Ágúst Úlfsson",
    "isrc": "ISA220801581"
  },
  {
    "title": "Fíllinn og hunangsflugan",
    "artist": "Ævar R. Kvaran",
    "isrc": "ISA110304204"
  },
  {
    "title": "Kalli kemur inn um gluggann hans Bróa",
    "artist": "Leikhópurinn Kalli á þakinu",
    "isrc": "ISA220900284"
  },
  {
    "title": "Skemmtidagskrá",
    "artist": "Leikhópurinn Kardemommubærinn",
    "isrc": "ISA111000109"
  },
  {
    "title": "Blóðeitrunin",
    "artist": "Ýmsir leikarar",
    "isrc": "ISA109205911"
  },
  {
    "title": "Frú Prússólín kemur í heimsókn",
    "artist": "Leikhópurinn Lína Langsokkur, Geirfuglarnir, Borgarleikhúsið",
    "isrc": "ISA220900169"
  },
  {
    "title": "Dýrin í Þykjustulandi",
    "artist": "Glámur og Skrámur",
    "isrc": "ISA109200607"
  },
  {
    "title": "Dátinn og nornin",
    "artist": "Guðjón Davíð Karlsson",
    "isrc": "ISA111201003"
  },
  {
    "title": "Annar Kafli",
    "artist": "Heiðdís Norðfjörð",
    "isrc": "ISA110707803"
  },
  {
    "title": "Sagan af Argin-tætu",
    "artist": "Anna Pálína, Aðalsteinn Ásberg",
    "isrc": "ISZ109800309"
  },
  {
    "title": "Rauðhetta",
    "artist": "Grimmsævintýrahópurinn",
    "isrc": "ISA110304602"
  },
  {
    "title": "Þrír bangsar",
    "artist": "Bessi Bjarnason",
    "isrc": "ISA110701602"
  },
  {
    "title": "Svalur Gúrka (saga)",
    "artist": "Jóhann Sigurðarson",
    "isrc": "ISV442409504"
  },
  {
    "title": "Faðir vor kallar kútinn",
    "artist": "Sigurður Sigurjónsson",
    "isrc": "ISA110303602"
  },
  {
    "title": "úr Skjóðunni (2)",
    "artist": "Þorvaldur Þorsteinsson, Jóhann G. Jóhannsson",
    "isrc": "QZDA72078499"
  },
  {
    "title": "Fingranöfnin",
    "artist": "Skoppa og Skrítla",
    "isrc": "ISA110701909"
  },
  {
    "title": "Geiturnar þrjár",
    "artist": "Kristjana Skúladóttir, Sögustund.is",
    "isrc": "ISV442010106"
  },
  {
    "title": "Mjallhvít",
    "artist": "Úr leikriti",
    "isrc": "ISA109602701"
  },
  {
    "title": "Krakkarnir í Kátugötu - bók 2",
    "artist": "Samgöngustofa",
    "isrc": "ISV442005802"
  },
  {
    "title": "Draumur",
    "artist": "Sprotarnir",
    "isrc": "ISV441724804"
  },
  {
    "title": "Stafakarlalagið",
    "artist": "Bergljót Arnalds",
    "isrc": "ISA110807401"
  },
  {
    "title": "Sívert og Andrés kynnast",
    "artist": "Leikhópurinn Síglaðir söngvarar",
    "isrc": "ISA111000403"
  },
  {
    "title": "Þannig fór að lokum",
    "artist": "Leikhópurinn Karíus, Baktus",
    "isrc": "ISA111000209"
  },
  {
    "title": "Gosi seldur í leikhúsið",
    "artist": "Karl Ágúst Úlfsson",
    "isrc": "ISA220801592"
  },
  {
    "title": "Velvakandi og bræður hans",
    "artist": "Ævar R. Kvaran",
    "isrc": "ISA110304202"
  },
  {
    "title": "Kalli lasinn á afmælinu sínu",
    "artist": "Leikhópurinn Kalli á þakinu",
    "isrc": "ISA220900286"
  },
  {
    "title": "Kardemommuhátíð",
    "artist": "Leikhópurinn Kardemommubærinn",
    "isrc": "ISA111000107"
  },
  {
    "title": "Litli prinsinn",
    "artist": "Ýmsir leikarar",
    "isrc": "ISG220900171"
  },
  {
    "title": "Anna og Tommi hitta Línu",
    "artist": "Leikhópurinn Lína Langsokkur",
    "isrc": "ISA220900168"
  },
  {
    "title": "Dátinn í borginni",
    "artist": "Guðjón Davíð Karlsson",
    "isrc": "ISA111201005"
  },
  {
    "title": "Fjórði kafli",
    "artist": "Heiðdís Norðfjörð",
    "isrc": "ISA110707807"
  },
  {
    "title": "Hérin og skjaldbakan",
    "artist": "Bessi Bjarnason",
    "isrc": "ISA110701605"
  },
  {
    "title": "Hans og Gréta",
    "artist": "Grimmsævintýrahópurinn",
    "isrc": "ISA110304501"
  }
]