[
  {
    "title": "Soul Devourer",
    "artist": "Suffering Souls",
    "isrc": "QM6MZ2487709"
  },
  {
    "title": "Scarification",
    "artist": "Cryptik Howling",
    "isrc": "uscgj1029945"
  },
  {
    "title": "Shadows Amongst the Moonlight",
    "artist": "Inquinok",
    "isrc": "TCABG1272425"
  },
  {
    "title": "Metalstorm/Face the Slayer",
    "artist": "Thy Infernal",
    "isrc": "USI4R0701092"
  },
  {
    "title": "Ghost of The Ancient Siberian Wolfcult",
    "artist": "Liar Of Golgotha",
    "isrc": "ES7580700566"
  },
  {
    "title": "Gates of Experience, Part I",
    "artist": "Nebular Moon",
    "isrc": "GX8KD2246899"
  },
  {
    "title": "The Infinite Dance of Numbers",
    "artist": "Quintessence Mystica",
    "isrc": "DEDL11412014"
  },
  {
    "title": "In Memoriam",
    "artist": "Obscurcis Romancia",
    "isrc": "CA6NS1100007"
  },
  {
    "title": "Hyperthalamic Prey",
    "artist": "Amortis",
    "isrc": "GBDHS0904303"
  },
  {
    "title": "At the Gates of Creation",
    "artist": "Astral Winter",
    "isrc": "UKXN22067566"
  },
  {
    "title": "Nocturnal Wanderer",
    "artist": "Ceremonial Embrace",
    "isrc": "QMFME2257338"
  },
  {
    "title": "Opening The Shrine Of Lanus",
    "artist": "Mystical Fullmoon",
    "isrc": "USHM20788013"
  },
  {
    "title": "Embodiment of Evil",
    "artist": "Atra Universum",
    "isrc": "usx9p1276213"
  },
  {
    "title": "Violence Reigns Supreme",
    "artist": "Winter Of Sin",
    "isrc": "UKCVA1902036"
  },
  {
    "title": "In the Silence ov Tehom",
    "artist": "Infernal Angels",
    "isrc": "QZYXP2309571"
  },
  {
    "title": "Stormwinds of Lucifer",
    "artist": "Reign Of Erebus",
    "isrc": "GBDHS0100122"
  },
  {
    "title": "To Become What It Became",
    "artist": "Stigmatheist",
    "isrc": "DKFDD9900201"
  },
  {
    "title": "Into Black Abyss",
    "artist": "Eclipse Eternal",
    "isrc": "CAI370815038"
  },
  {
    "title": "Glories Of The Nightsky",
    "artist": "Astriaal",
    "isrc": "AUOR30800604"
  },
  {
    "title": "Dreambook",
    "artist": "Eternal Silence",
    "isrc": "GBLFP1521474"
  },
  {
    "title": "Last Breath",
    "artist": "Damnation Army",
    "isrc": "NLB930900322"
  },
  {
    "title": "Purification",
    "artist": "Fall Ov Serafim",
    "isrc": "SEVCK0511002"
  },
  {
    "title": "The Great Heathen Army",
    "artist": "Gevaudan",
    "isrc": "GBKPL1966121"
  },
  {
    "title": "The Wanderer",
    "artist": "Goathemy",
    "isrc": "FIRB50700001"
  },
  {
    "title": "Atrocity Upon Deception",
    "artist": "Grievance",
    "isrc": "NOFVH9854030"
  },
  {
    "title": "The Cruel Bard Suite: Saga Of The Shield-Maid",
    "artist": "Heresiarh",
    "isrc": "GBJBV0700438"
  },
  {
    "title": "WOLVES - Radio Edit",
    "artist": "Lord Kaos",
    "isrc": "QZFZ62401376"
  },
  {
    "title": "Intent the Proem",
    "artist": "Hæresiarchs Of Dis",
    "isrc": "USGE31015702"
  },
  {
    "title": "The Hunting",
    "artist": "Immortal Remains",
    "isrc": "ITD240904403"
  },
  {
    "title": "From Misery...",
    "artist": "In Memorium",
    "isrc": "USA560617745"
  },
  {
    "title": "Essence of Evil",
    "artist": "Mhorgl",
    "isrc": "AUEA31000512"
  },
  {
    "title": "The Spiritually Neutral",
    "artist": "Morior Ergo Sum",
    "isrc": "USI4R0914999"
  },
  {
    "title": "Лучше",
    "artist": "Nefertum",
    "isrc": "FR26V2015547"
  },
  {
    "title": "Supreme Black Victory",
    "artist": "Perpetual Dusk",
    "isrc": "BRCOG0500206"
  },
  {
    "title": "Requiem Aeternam - Instrumental Extension",
    "artist": "Requiem Aeternam",
    "isrc": "QZNWY2398459"
  },
  {
    "title": "Bloedkloete",
    "artist": "Salacious Gods",
    "isrc": "NLWJ22300416"
  },
  {
    "title": "Saksen",
    "artist": "Saxorior",
    "isrc": "DEZ901501644"
  },
  {
    "title": "Change",
    "artist": "ShadowCraft",
    "isrc": "AUQE10900017"
  },
  {
    "title": "Static Development",
    "artist": "Source Of Tide",
    "isrc": "GBADD0406301"
  },
  {
    "title": "Dark Prophecies",
    "artist": "Subliritum",
    "isrc": "ushm91112440"
  },
  {
    "title": "I Will Not Fail",
    "artist": "The Heretic",
    "isrc": "QZHN32007364"
  },
  {
    "title": "Fire Serpent Dawn",
    "artist": "Thus Defiled",
    "isrc": "uscgh1684756"
  },
  {
    "title": "The Picture",
    "artist": "Voices of Decay",
    "isrc": "ITA502010107"
  },
  {
    "title": "A Touch Of Evil Kindness",
    "artist": "Suffering Souls",
    "isrc": "QM6MZ2487713"
  },
  {
    "title": "Between",
    "artist": "Cryptik Howling",
    "isrc": "uscgj1029943"
  },
  {
    "title": "Night Terror",
    "artist": "Inquinok",
    "isrc": "TCAEE1969954"
  },
  {
    "title": "Night of The Falling Stars",
    "artist": "Liar Of Golgotha",
    "isrc": "ES7580700567"
  },
  {
    "title": "Der Ketzer Und Das Kind",
    "artist": "Nebular Moon",
    "isrc": "ATC150122601"
  },
  {
    "title": "Rotting in Hell",
    "artist": "Thy Infernal",
    "isrc": "ATN260109402"
  },
  {
    "title": "Vector Space of Desires",
    "artist": "Quintessence Mystica",
    "isrc": "DEDL11112001"
  },
  {
    "title": "Godless Aphrodite",
    "artist": "Amortis",
    "isrc": "GBDHS0904301"
  },
  {
    "title": "Here Comes The Storm",
    "artist": "Obscurcis Romancia",
    "isrc": "CA6NS2100001"
  },
  {
    "title": "Beyond These Frozen Castle Walls",
    "artist": "Astral Winter",
    "isrc": "QMEZE1717093"
  },
  {
    "title": "Mysterious Fate",
    "artist": "Ceremonial Embrace",
    "isrc": "QMFME2257335"
  },
  {
    "title": "As I Walk Along The Dark Paths Of My Soul",
    "artist": "Mystical Fullmoon",
    "isrc": "USHM20788010"
  },
  {
    "title": "Soldiers Of The Underworld",
    "artist": "Atra Universum",
    "isrc": "usx9p0716318"
  },
  {
    "title": "Astral Death Reign Algorithm",
    "artist": "Winter Of Sin",
    "isrc": "UKCVA1902033"
  },
  {
    "title": "The Horizon Eats the Sun and Other Stars",
    "artist": "Infernal Angels",
    "isrc": "QZYXP2309572"
  },
  {
    "title": "As The Clouds Gather",
    "artist": "Reign Of Erebus",
    "isrc": "QZNWU2080159"
  },
  {
    "title": "Within the Pains of Pleasure",
    "artist": "Stigmatheist",
    "isrc": "DKFDD9900202"
  },
  {
    "title": "Deathbound",
    "artist": "Eclipse Eternal",
    "isrc": "CAI371200267"
  },
  {
    "title": "Ritual Hate Construct",
    "artist": "Astriaal",
    "isrc": "AUOR30800602"
  },
  {
    "title": "Prayer of the Resilient",
    "artist": "Eternal Silence",
    "isrc": "IT8SF2300289"
  },
  {
    "title": "A Dagger Right In Your Heart",
    "artist": "Damnation Army",
    "isrc": "NLB930600081"
  },
  {
    "title": "Towards the Throne of Tragedy",
    "artist": "Fall Ov Serafim",
    "isrc": "SEVCK0511001"
  },
  {
    "title": "Maelstrom",
    "artist": "Gevaudan",
    "isrc": "GBKPL1966120"
  },
  {
    "title": "Dead Man's Ashes",
    "artist": "Goathemy",
    "isrc": "FIRB50700007"
  },
  {
    "title": "Angels Succumb",
    "artist": "Grievance",
    "isrc": "NOFVH9854020"
  },
  {
    "title": "Dragons Domain",
    "artist": "Heresiarh",
    "isrc": "GBJBV0700436"
  },
  {
    "title": "Ensorcelled by Khaos",
    "artist": "Hæresiarchs Of Dis",
    "isrc": "USGE31016307"
  },
  {
    "title": "Everlasting Night",
    "artist": "Immortal Remains",
    "isrc": "ITD240904404"
  },
  {
    "title": "Ravenslaughter",
    "artist": "In Memorium",
    "isrc": "USA560617744"
  },
  {
    "title": "Dark Satanic Blasphemy",
    "artist": "Suffering Souls",
    "isrc": "DEDL12109030"
  },
  {
    "title": "From Ephemeral Pain to Everlasting Anguish",
    "artist": "Cryptik Howling",
    "isrc": "ushm91264855"
  },
  {
    "title": "The Altar",
    "artist": "Inquinok",
    "isrc": "TCAEE1969975"
  },
  {
    "title": "Fleischeslust",
    "artist": "Nebular Moon",
    "isrc": "ATC150122608"
  },
  {
    "title": "In Praise of Cthulhu",
    "artist": "Liar Of Golgotha",
    "isrc": "ES7580700571"
  },
  {
    "title": "Triumph of Cold Steel",
    "artist": "Quintessence Mystica",
    "isrc": "DEDL11112002"
  },
  {
    "title": "For the Glory of Satan",
    "artist": "Thy Infernal",
    "isrc": "USA560526737"
  },
  {
    "title": "Exit Wound 187",
    "artist": "Amortis",
    "isrc": "GBDHS0904307"
  },
  {
    "title": "Seasons Of Infinite Sorrow",
    "artist": "Obscurcis Romancia",
    "isrc": "CA6NS1100008"
  },
  {
    "title": "The Rain Falls Upon This Distant Land",
    "artist": "Astral Winter",
    "isrc": "ESA012157155"
  },
  {
    "title": "Last Remains of the Pathetic",
    "artist": "Ceremonial Embrace",
    "isrc": "QMFME2257337"
  },
  {
    "title": "Per Speculum In Aenigmate",
    "artist": "Mystical Fullmoon",
    "isrc": "USHM20788012"
  },
  {
    "title": "Anti-Life",
    "artist": "Atra Universum",
    "isrc": "usx9p1276216"
  },
  {
    "title": "Maelstrom",
    "artist": "Winter Of Sin",
    "isrc": "UKCVA1902034"
  },
  {
    "title": "And All Shall Fade With Time",
    "artist": "Reign Of Erebus",
    "isrc": "QZNWU2080163"
  }
]