[
  {
    "title": "Clean My Wounds",
    "artist": "Corrosion Of Conformity",
    "isrc": "USSM10022697"
  },
  {
    "title": "Wizard Fight",
    "artist": "Weedeater",
    "isrc": "FR33T1332302"
  },
  {
    "title": "Blackened",
    "artist": "Toke",
    "isrc": "TCACW1619173"
  },
  {
    "title": "At A Loss",
    "artist": "Buzzov•en, Dave Dixie Collins",
    "isrc": "QZJG51945079"
  },
  {
    "title": "Monochrome",
    "artist": "Between The Buried And Me",
    "isrc": "USYFZ2145401"
  },
  {
    "title": "Avian Dawn",
    "artist": "Sourvein",
    "isrc": "USMBR1511506"
  },
  {
    "title": "Sonnet",
    "artist": "Prayer For Cleansing",
    "isrc": "QMVTG1100011"
  },
  {
    "title": "In Between the Sheets",
    "artist": "Glass Casket",
    "isrc": "GBDHC0432008"
  },
  {
    "title": "Right Death Before",
    "artist": "ASG",
    "isrc": "USVE30700454"
  },
  {
    "title": "Penance",
    "artist": "Mo'ynoq",
    "isrc": "QZNWQ2291939"
  },
  {
    "title": "This Day All Gods Die",
    "artist": "Undying",
    "isrc": "TCAGL2268019"
  },
  {
    "title": "Dilated Disappointment",
    "artist": "Wretched",
    "isrc": "USVIC1266804"
  },
  {
    "title": "Fortune and Glory",
    "artist": "Mega Colossus",
    "isrc": "ITI292400101"
  },
  {
    "title": "The Vomit Hounds",
    "artist": "Eldritch Horror",
    "isrc": "usdy41528590"
  },
  {
    "title": "Put a Sock in It",
    "artist": "Killwhitneydead",
    "isrc": "QMVTG1100765"
  },
  {
    "title": "Duplicity",
    "artist": "Krosis",
    "isrc": "QM4TX1921786"
  },
  {
    "title": "Festering Anal Vomit",
    "artist": "Lust of Decay",
    "isrc": "USY252401177"
  },
  {
    "title": "Sieg Zeon!",
    "artist": "Children of the Reptile",
    "isrc": "GB-SMU-51-73988"
  },
  {
    "title": "Call To Satan",
    "artist": "Hour Of 13",
    "isrc": "GB-SMU-32-06611"
  },
  {
    "title": "Devilwolf (Bound Til Death)",
    "artist": "All Hell",
    "isrc": "QZTB72303162"
  },
  {
    "title": "Heatseeker",
    "artist": "Valient Thorr",
    "isrc": "USVE30600315"
  },
  {
    "title": "Insular World",
    "artist": "Mortal Man",
    "isrc": "USCGH2415263"
  },
  {
    "title": "Break the silence",
    "artist": "Bloodjinn",
    "isrc": "FR1PP0700560"
  },
  {
    "title": "Visualize Industrial Collapse",
    "artist": "Day Of Suffering",
    "isrc": "GB-SMU-40-76326"
  },
  {
    "title": "Wolf's Jaw",
    "artist": "Onward To Olympas",
    "isrc": "US38J1212203"
  },
  {
    "title": "Beneath the Machine",
    "artist": "Sanctity",
    "isrc": "NLA320784080"
  },
  {
    "title": "1000 Fucks Not Given",
    "artist": "Divine Treachery",
    "isrc": "TCAED1933692"
  },
  {
    "title": "Reprieves for My Enemies",
    "artist": "Debodified",
    "isrc": "USY252401372"
  },
  {
    "title": "End of Days",
    "artist": "Demon Eye",
    "isrc": "DEZ901501129"
  },
  {
    "title": "Death",
    "artist": "Æther Realm",
    "isrc": "TCADB1712237"
  },
  {
    "title": "The South Is Rising",
    "artist": "The Sign of the Southern Cross",
    "isrc": "FR33T0918603"
  },
  {
    "title": "Denim Destiny",
    "artist": "Thunderlip",
    "isrc": "USDLJ0700003"
  },
  {
    "title": "Prison Planet",
    "artist": "Gross Reality",
    "isrc": "QZNWW2396054"
  },
  {
    "title": "Stage 2: The Captive",
    "artist": "The Reticent",
    "isrc": "usl4q2072110"
  },
  {
    "title": "Betrayed by Light",
    "artist": "Young And In The Way",
    "isrc": "QZHNA1968187"
  },
  {
    "title": "The Marionette",
    "artist": "The Demonstration",
    "isrc": "USFK90800117"
  },
  {
    "title": "The Gateway",
    "artist": "Paezor",
    "isrc": "QZHN52025923"
  },
  {
    "title": "Snarling of Beasts",
    "artist": "Bedowyn",
    "isrc": "USA2P1339671"
  },
  {
    "title": "Obsidian Knife",
    "artist": "Salvación",
    "isrc": "USTLD1300003"
  },
  {
    "title": "Blood in the Water",
    "artist": "Black Ritual",
    "isrc": "QZ22B1753327"
  },
  {
    "title": "What's Done Is Done",
    "artist": "Written in Gray",
    "isrc": "SE6A91807729"
  },
  {
    "title": "Strange",
    "artist": "Kill Devil Hill",
    "isrc": "AUNV41300126"
  },
  {
    "title": "Ingesting Her Liquefied Remains",
    "artist": "$lutrot",
    "isrc": "QZDA81918642"
  },
  {
    "title": "Believe in Black",
    "artist": "Hail!Hornet",
    "isrc": "USEWC0712115"
  },
  {
    "title": "El Gibbor",
    "artist": "Bloodline Severed",
    "isrc": "QZK6N2099899"
  },
  {
    "title": "Let Sleeping Corpses Lie",
    "artist": "Bloody Hammers",
    "isrc": "ATN261986701"
  },
  {
    "title": "Condemned",
    "artist": "Confessor",
    "isrc": "GBBPB0700263"
  },
  {
    "title": "Slaughtering Sin",
    "artist": "Blood Thirsty",
    "isrc": "QM2PV1630101"
  },
  {
    "title": "The Dead of Night",
    "artist": "Walpyrgus",
    "isrc": "USGRX1721101"
  },
  {
    "title": "Instipuous Malpractification Amonst Abnomolical Dextrosity",
    "artist": "Vituperate",
    "isrc": "USY252316073"
  },
  {
    "title": "Sodomizing the Elderly",
    "artist": "Cesspool of Vermin",
    "isrc": "USI4R0815643"
  },
  {
    "title": "Impaled on the Communist's Spear",
    "artist": "Sankara",
    "isrc": "QZES51945665"
  },
  {
    "title": "Longhammer",
    "artist": "Undrask",
    "isrc": "QZ4JJ1668155"
  },
  {
    "title": "Illa, Mother of Death",
    "artist": "Feminazgul",
    "isrc": "QZFZ72071353"
  },
  {
    "title": "Battered Whore Butchery",
    "artist": "Decimated Humans",
    "isrc": "USY251499451"
  },
  {
    "title": "Open Grave",
    "artist": "Worsen",
    "isrc": "QZHN72082875"
  },
  {
    "title": "Glass",
    "artist": "Chaosmic",
    "isrc": "QM4XK1500006"
  },
  {
    "title": "The Living Tide",
    "artist": "Solar Halos",
    "isrc": "uscgj1907600"
  },
  {
    "title": "A Mist of Heaven Inside of Hell",
    "artist": "Oculum Dei, Amanda Mcgraw",
    "isrc": "QZDA51903063"
  },
  {
    "title": "Infestation",
    "artist": "Bloodsoaked",
    "isrc": "USY252402570"
  },
  {
    "title": "Good Old Fashioned Passionate Ass Thrashin'",
    "artist": "Acirema",
    "isrc": "US28Y0904202"
  },
  {
    "title": "Of Wolf and Man",
    "artist": "Vanisher",
    "isrc": "QMVTG1200041"
  },
  {
    "title": "Holy Wars...The Punishment Due",
    "artist": "Blatant Disarray",
    "isrc": "QMVTG1200039"
  },
  {
    "title": "Ghosting",
    "artist": "Daylight Dies",
    "isrc": "GBADD1228306"
  },
  {
    "title": "Born",
    "artist": "Atten Ash",
    "isrc": "uscgh1538665"
  },
  {
    "title": "Tigerlilly",
    "artist": "Crystal Spiders",
    "isrc": "USY252022211"
  },
  {
    "title": "Diarrhea Creampie",
    "artist": "Cheerleader Concubine",
    "isrc": "QZ4H21800069"
  },
  {
    "title": "Exterminate the Apostles",
    "artist": "Atrocious Abnormality",
    "isrc": "USY252401205"
  },
  {
    "title": "Purity Shrouded in Putrefaction",
    "artist": "Purulent Necrosis",
    "isrc": "USY252008959"
  },
  {
    "title": "Solaruss",
    "artist": "Ape Vermin",
    "isrc": "USHM22472699"
  },
  {
    "title": "I Leave You With Six Words",
    "artist": "A Vision Grotesque",
    "isrc": "ushm20779465"
  },
  {
    "title": "Ripped From a Mother's Mutilated Womb",
    "artist": "Abhorrent Deformity",
    "isrc": "USY252401673"
  },
  {
    "title": "Different Day",
    "artist": "Aittala",
    "isrc": "QZ5FN2359454"
  },
  {
    "title": "Dark Dreamer",
    "artist": "Atma Weapon",
    "isrc": "ushm81311832"
  },
  {
    "title": "Jordan Jamal Joe Jeffery Jackson III",
    "artist": "Beastial Piglord",
    "isrc": "QZFZ72497284"
  },
  {
    "title": "Darkest Knight",
    "artist": "Blackwatch, D-Charged",
    "isrc": "DEAR41519008"
  },
  {
    "title": "Devoured by Wolves",
    "artist": "Brainsludge",
    "isrc": "QZES62061244"
  },
  {
    "title": "Birdsong",
    "artist": "Caltrop",
    "isrc": "USA2B1204101"
  },
  {
    "title": "Doomed to Wander",
    "artist": "Codex Obscura",
    "isrc": "QZPLR2260261"
  },
  {
    "title": "Our Creation",
    "artist": "Columns",
    "isrc": "US2641425504"
  },
  {
    "title": "Endless Struggle",
    "artist": "Curse Your Name",
    "isrc": "USDHM0800516"
  },
  {
    "title": "Don't Panic",
    "artist": "DEMIURGE",
    "isrc": "QM24S2001372"
  },
  {
    "title": "Green Machine",
    "artist": "Darth Kannabyss",
    "isrc": "QZES92075180"
  },
  {
    "title": "Bloodmoney",
    "artist": "DethCadence",
    "isrc": "ushm81965968"
  },
  {
    "title": "Charisma",
    "artist": "Dogbane",
    "isrc": "USY251402419"
  },
  {
    "title": "Essence of Brutality",
    "artist": "Domination through Impurity",
    "isrc": "USY252401418"
  },
  {
    "title": "Drawn to Drown",
    "artist": "Dreaded",
    "isrc": "QM2PV1691048"
  },
  {
    "title": "World of Malice",
    "artist": "Dreamscapes Of The Perverse",
    "isrc": "QMVTG1100143"
  },
  {
    "title": "La Madre Del Vicio",
    "artist": "Edge of Humanity",
    "isrc": "QM9AA1630085"
  },
  {
    "title": "The Citizen Patrol",
    "artist": "Eugenic Death",
    "isrc": "usdy41913338"
  },
  {
    "title": "Replace God..Conceal The Beast",
    "artist": "Final Curse",
    "isrc": "USDHM1209522"
  },
  {
    "title": "Like Somthing Rolling Downhill, It All Went Downhill Pretty Fast",
    "artist": "Funeral for a Wizard",
    "isrc": "QZK6K2009379"
  },
  {
    "title": "Hardureiks",
    "artist": "Germanic Iron",
    "isrc": "QZFYX2025001"
  },
  {
    "title": "Hinge",
    "artist": "Hadea",
    "isrc": "DKQ4A1305201"
  },
  {
    "title": "Neocortical Lateral Transference",
    "artist": "Hellbroth",
    "isrc": "usx9p1043036"
  },
  {
    "title": "Malice in Wonderland",
    "artist": "Hephystus",
    "isrc": "ushm81310339"
  },
  {
    "title": "Outlaw Wolf Fire",
    "artist": "Horseskull",
    "isrc": "QM9AA1437361"
  },
  {
    "title": "Return of Affliction",
    "artist": "In-Defilade, Dallas Toler-Wade",
    "isrc": "QZ9Y21741680"
  },
  {
    "title": "Vow of Destruction",
    "artist": "Iōhannēs",
    "isrc": "CACWV2399935"
  },
  {
    "title": "Last Train to Rio",
    "artist": "Killer Khan",
    "isrc": "QZ8251926168"
  },
  {
    "title": "I Knew You Were Trouble",
    "artist": "Killing the Catalyst",
    "isrc": "QZ9JZ1780242"
  },
  {
    "title": "The Monster",
    "artist": "Knightmare, Black Falcun, Syren Militia",
    "isrc": "usl4q1727165"
  },
  {
    "title": "Degrading Succession",
    "artist": "Malebolgia",
    "isrc": "USY252402816"
  },
  {
    "title": "No Visible Light",
    "artist": "Mourning Cloak",
    "isrc": "QM4TX1893304"
  },
  {
    "title": "Trial By Fire",
    "artist": "Nameless Anonymous",
    "isrc": "USA2P2218040"
  },
  {
    "title": "Soul Deceiver",
    "artist": "Nemesis Alpha",
    "isrc": "ITN581901610"
  },
  {
    "title": "Adamantine",
    "artist": "New Light Choir",
    "isrc": "FRX201808712"
  },
  {
    "title": "Saprophyte",
    "artist": "Nox Eternus",
    "isrc": "QZPLR2397424"
  },
  {
    "title": "Divine Motion",
    "artist": "Old Moons",
    "isrc": "GB-SMU-56-12122"
  },
  {
    "title": "The Blackest Dawn",
    "artist": "Outliar",
    "isrc": "QMAAK1884584"
  },
  {
    "title": "Keeper of the Flame",
    "artist": "Overlord SR",
    "isrc": "GBWUL2215488"
  },
  {
    "title": "Severed Head",
    "artist": "Rictus Grin",
    "isrc": "usdy41654637"
  },
  {
    "title": "Waveform 66",
    "artist": "Rites to Sedition",
    "isrc": "QMPKX1745677"
  },
  {
    "title": "Deceit and Desire",
    "artist": "Steryle",
    "isrc": "uscgh1288430"
  },
  {
    "title": "Kiss from a Rose",
    "artist": "Tattermask",
    "isrc": "QM8271400003"
  },
  {
    "title": "One Shot Down",
    "artist": "Thundering Herd",
    "isrc": "TCABQ1394440"
  },
  {
    "title": "A Storm of Rosen Mare and Black Chalice",
    "artist": "Witches Moon",
    "isrc": "QZES82062755"
  },
  {
    "title": "The Dirge of Fallen Warriors",
    "artist": "Wrath And Rapture",
    "isrc": "USF270706202"
  },
  {
    "title": "It Is Lifted",
    "artist": "întristare, Cammy Barnes",
    "isrc": "QZHN51990302"
  },
  {
    "title": "Vote with a Bullet",
    "artist": "Corrosion Of Conformity",
    "isrc": "USSM10022669"
  },
  {
    "title": "God Luck and Good Speed",
    "artist": "Weedeater",
    "isrc": "FR33T1332301"
  },
  {
    "title": "Weight of the World",
    "artist": "Toke",
    "isrc": "TCACW1619172"
  },
  {
    "title": "Dont Bring Me Down",
    "artist": "Buzzov•en",
    "isrc": "QZJG51945086"
  },
  {
    "title": "Foam Born (A) The Backtrack",
    "artist": "Between The Buried And Me",
    "isrc": "USVIC0735101"
  },
  {
    "title": "Fangs",
    "artist": "Sourvein",
    "isrc": "GBADD1134201"
  },
  {
    "title": "Feinbhas a Ghabhail",
    "artist": "Prayer For Cleansing",
    "isrc": "QMVTG1100008"
  },
  {
    "title": "Pencil Lead Syringe",
    "artist": "Glass Casket",
    "isrc": "GBDHC0432001"
  },
  {
    "title": "Throes of Ardent Disposition",
    "artist": "Mo'ynoq",
    "isrc": "QZK6K2250450"
  },
  {
    "title": "Crosses",
    "artist": "ASG",
    "isrc": "USVE30300019"
  },
  {
    "title": "Echoes",
    "artist": "Undying",
    "isrc": "DEAF71104461"
  },
  {
    "title": "The Stellar Sunset Of Evolution Pt. 2 (The Rise)",
    "artist": "Wretched",
    "isrc": "USVIC1266808"
  },
  {
    "title": "Wicked Road",
    "artist": "Mega Colossus",
    "isrc": "ITI292400105"
  },
  {
    "title": "Unknown Graves",
    "artist": "Eldritch Horror",
    "isrc": "usdy41528593"
  },
  {
    "title": "Let Me Give You a Hand Throwing Yourself Out",
    "artist": "Killwhitneydead",
    "isrc": "QMVTG1100739"
  },
  {
    "title": "Battles Are Won Within",
    "artist": "Krosis",
    "isrc": "QM7281905212"
  },
  {
    "title": "Erased from Existence",
    "artist": "Lust of Decay",
    "isrc": "USY252401180"
  },
  {
    "title": "Burner",
    "artist": "Children of the Reptile",
    "isrc": "QZFZ72358873"
  },
  {
    "title": "Grim Reality",
    "artist": "Hour Of 13",
    "isrc": "GB-SMU-32-06615"
  },
  {
    "title": "Suffer for Me",
    "artist": "All Hell",
    "isrc": "QZES52376646"
  },
  {
    "title": "Heed the Call",
    "artist": "Mortal Man",
    "isrc": "USCGH2415265"
  },
  {
    "title": "Man Behind The Curtain",
    "artist": "Valient Thorr",
    "isrc": "US39N0500162"
  },
  {
    "title": "Inhale exhale",
    "artist": "Bloodjinn",
    "isrc": "FR1PP0700630"
  },
  {
    "title": "The Eternal Jihad",
    "artist": "Day Of Suffering",
    "isrc": "GB-SMU-41-29639"
  },
  {
    "title": "Strange Forest",
    "artist": "Onward To Olympas",
    "isrc": "US38J1212202"
  },
  {
    "title": "Zeppo",
    "artist": "Sanctity",
    "isrc": "NLA320784092"
  },
  {
    "title": "3 in the Pit",
    "artist": "Divine Treachery",
    "isrc": "TCAED1933711"
  },
  {
    "title": "Embludgeoned Between Crunches",
    "artist": "Debodified",
    "isrc": "USY252401378"
  },
  {
    "title": "The Waters and the Wild",
    "artist": "Demon Eye",
    "isrc": "DEZ901700315"
  },
  {
    "title": "Guardian",
    "artist": "Æther Realm",
    "isrc": "ATN262087805"
  },
  {
    "title": "Eating the Sun",
    "artist": "The Sign of the Southern Cross",
    "isrc": "FR33T0918608"
  },
  {
    "title": "The Prophecy",
    "artist": "Thunderlip",
    "isrc": "USDLJ0700005"
  },
  {
    "title": "Mind At Large",
    "artist": "Gross Reality",
    "isrc": "QZNWW2396055"
  },
  {
    "title": "Stage 1: His Name Is Henry",
    "artist": "The Reticent",
    "isrc": "usl4q2072109"
  },
  {
    "title": "Fuck This Life",
    "artist": "Young And In The Way",
    "isrc": "QZHNA1968188"
  },
  {
    "title": "Deadpan",
    "artist": "The Demonstration",
    "isrc": "USFK90800118"
  },
  {
    "title": "The Chaos Witch",
    "artist": "Paezor",
    "isrc": "QZHN52025924"
  },
  {
    "title": "Rite to Kill",
    "artist": "Bedowyn",
    "isrc": "USA2P1548482"
  },
  {
    "title": "Take Control",
    "artist": "Salvación",
    "isrc": "uscgj1825401"
  },
  {
    "title": "Sick 66",
    "artist": "Black Ritual",
    "isrc": "QZ22B1753326"
  },
  {
    "title": "Sanguine Rose",
    "artist": "Written in Gray",
    "isrc": "SE5BU2081815"
  },
  {
    "title": "War Machine",
    "artist": "Kill Devil Hill",
    "isrc": "AUNV41300120"
  },
  {
    "title": "$quad Up!",
    "artist": "$lutrot",
    "isrc": "QZDA81918643"
  },
  {
    "title": "Golden Whore",
    "artist": "Hail!Hornet",
    "isrc": "USEWC0712116"
  },
  {
    "title": "Harvest of Souls",
    "artist": "Bloodline Severed",
    "isrc": "QZK6N2099900"
  },
  {
    "title": "Alone",
    "artist": "Confessor",
    "isrc": "GBBPB0700258"
  },
  {
    "title": "Twilight Zone",
    "artist": "Bloody Hammers",
    "isrc": "QZDA52195944"
  },
  {
    "title": "Omniscient",
    "artist": "Blood Thirsty",
    "isrc": "QM2PV1630105"
  },
  {
    "title": "Dead Girls",
    "artist": "Walpyrgus",
    "isrc": "USGRX1721103"
  },
  {
    "title": "Declithtronicism Hypermalfistic Parasitic Catastrophe",
    "artist": "Vituperate",
    "isrc": "USY252316077"
  },
  {
    "title": "Bestial Necrophilia",
    "artist": "Cesspool of Vermin",
    "isrc": "USI4R0815639"
  },
  {
    "title": "The Blood and Bile of the Capitalist",
    "artist": "Sankara",
    "isrc": "QZES51945667"
  },
  {
    "title": "Eye of the Archdemon",
    "artist": "Undrask",
    "isrc": "QZES72375084"
  },
  {
    "title": "I Pity the Immortal",
    "artist": "Feminazgul",
    "isrc": "QZFZ72071354"
  },
  {
    "title": "Mortuary Fetishism",
    "artist": "Decimated Humans",
    "isrc": "USY251499450"
  },
  {
    "title": "Aspirations Rusted Shut",
    "artist": "Worsen",
    "isrc": "QZHN72082876"
  },
  {
    "title": "Desert Grave",
    "artist": "Chaosmic",
    "isrc": "QM4XK1500001"
  },
  {
    "title": "Conduit",
    "artist": "Solar Halos",
    "isrc": "uscgj1907604"
  },
  {
    "title": "Involuntary Pandemic",
    "artist": "Oculum Dei",
    "isrc": "QZDA51903057"
  },
  {
    "title": "Suicide",
    "artist": "Bloodsoaked",
    "isrc": "USY252402559"
  },
  {
    "title": "Wield The Axe And Sever The Head Of Hypocrisy",
    "artist": "Acirema",
    "isrc": "US28Y0904203"
  },
  {
    "title": "Born to Breed",
    "artist": "Vanisher",
    "isrc": "QMVTG1100164"
  },
  {
    "title": "Undetermined",
    "artist": "Blatant Disarray",
    "isrc": "QMVTG1100443"
  },
  {
    "title": "Dismantling Devotion",
    "artist": "Daylight Dies",
    "isrc": "GBADD0613308"
  },
  {
    "title": "See You...never",
    "artist": "Atten Ash",
    "isrc": "uscgh1538662"
  },
  {
    "title": "Trapped",
    "artist": "Crystal Spiders",
    "isrc": "USY252022209"
  },
  {
    "title": "Monster Girls Craving Monster Cock",
    "artist": "Cheerleader Concubine",
    "isrc": "QZ4H21800070"
  },
  {
    "title": "Failed Apocalypse",
    "artist": "Atrocious Abnormality",
    "isrc": "USY252401204"
  },
  {
    "title": "Induced Parasitic Gestation",
    "artist": "Purulent Necrosis",
    "isrc": "USY252008962"
  },
  {
    "title": "Awakened",
    "artist": "Ape Vermin",
    "isrc": "USHM22472704"
  },
  {
    "title": "Six Feet Tall, Six Feet Deep",
    "artist": "A Vision Grotesque",
    "isrc": "ushm20779466"
  },
  {
    "title": "A Populous Enslaved",
    "artist": "Abhorrent Deformity",
    "isrc": "QZES91841693"
  },
  {
    "title": "Collateral Damage",
    "artist": "Aittala",
    "isrc": "QZTRX2216496"
  },
  {
    "title": "Miss Misery",
    "artist": "Atma Weapon",
    "isrc": "ushm81311833"
  },
  {
    "title": "Not Provided",
    "artist": "Beastial Piglord",
    "isrc": "QZMER2111267"
  },
  {
    "title": "My Existence",
    "artist": "Blackwatch, Regain",
    "isrc": "DEAR41511929"
  },
  {
    "title": "Lust for Blood",
    "artist": "Brainsludge",
    "isrc": "QZK6K2128321"
  },
  {
    "title": "Light Does Not Get Old",
    "artist": "Caltrop",
    "isrc": "USA2B1204103"
  },
  {
    "title": "Control",
    "artist": "Codex Obscura",
    "isrc": "QZPLR2260272"
  },
  {
    "title": "No One's Fucking Waiting",
    "artist": "Columns",
    "isrc": "US2641425509"
  },
  {
    "title": "Albatross",
    "artist": "Corrosion Of Conformity",
    "isrc": "USSM10025014"
  },
  {
    "title": "Jason… the Dragon",
    "artist": "Weedeater",
    "isrc": "FR33T1332405"
  },
  {
    "title": "Legalize Sin",
    "artist": "Toke",
    "isrc": "TCACW1619175"
  },
  {
    "title": "A Lack Of",
    "artist": "Buzzov•en",
    "isrc": "QZJG51945080"
  },
  {
    "title": "Mordecai",
    "artist": "Between The Buried And Me",
    "isrc": "USVIC0321004"
  },
  {
    "title": "Ocypuss",
    "artist": "Sourvein",
    "isrc": "USMBR1511507"
  },
  {
    "title": "A Dead Soul Born",
    "artist": "Prayer For Cleansing",
    "isrc": "QMVTG1100010"
  },
  {
    "title": "Let Them Go",
    "artist": "Glass Casket",
    "isrc": "QZES62363471"
  },
  {
    "title": "The Collector",
    "artist": "Mo'ynoq",
    "isrc": "QZ8LD1904811"
  },
  {
    "title": "Dream Song",
    "artist": "ASG",
    "isrc": "USVE30700455"
  },
  {
    "title": "The company of storms",
    "artist": "Undying",
    "isrc": "DEAF71104463"
  },
  {
    "title": "Outrun Infinity",
    "artist": "Mega Colossus",
    "isrc": "ITI292400102"
  },
  {
    "title": "VI: The Exodus Of Autonomy - Instrumental",
    "artist": "Wretched",
    "isrc": "USVIC0950509"
  },
  {
    "title": "The Eternal Champion",
    "artist": "Eldritch Horror",
    "isrc": "usdy41528589"
  },
  {
    "title": "Skip the Break Up Get to the Make Up",
    "artist": "Killwhitneydead",
    "isrc": "QMVTG1100766"
  },
  {
    "title": "Amaranthus (Love Lies Bleeding)",
    "artist": "Krosis",
    "isrc": "QMDA62132949"
  },
  {
    "title": "Head in a Crock Pot",
    "artist": "Lust of Decay",
    "isrc": "USY252401178"
  },
  {
    "title": "Last Words (Ruin's Ride)",
    "artist": "Children of the Reptile",
    "isrc": "QZFZ72358877"
  },
  {
    "title": "The Correlation",
    "artist": "Hour Of 13",
    "isrc": "GB-SMU-32-06613"
  },
  {
    "title": "The Howl",
    "artist": "All Hell",
    "isrc": "QZTB72303161"
  },
  {
    "title": "Elixir",
    "artist": "Mortal Man",
    "isrc": "USCGH2415264"
  },
  {
    "title": "Double Crossed",
    "artist": "Valient Thorr",
    "isrc": "USVE31000821"
  },
  {
    "title": "In the first degree",
    "artist": "Bloodjinn",
    "isrc": "FR1PP0700550"
  },
  {
    "title": "Shades of Red",
    "artist": "Day Of Suffering",
    "isrc": "GB-SMU-40-76322"
  },
  {
    "title": "This World Is Not My Home",
    "artist": "Onward To Olympas",
    "isrc": "US38J1008910"
  },
  {
    "title": "Road to Bloodshed",
    "artist": "Sanctity",
    "isrc": "NLA320784088"
  },
  {
    "title": "Feed Breed Belittle",
    "artist": "Divine Treachery",
    "isrc": "TCAED1933717"
  },
  {
    "title": "Instinct for Malevolence",
    "artist": "Debodified",
    "isrc": "USY252401373"
  },
  {
    "title": "I'll Be Creeping",
    "artist": "Demon Eye",
    "isrc": "DEZ901501131"
  },
  {
    "title": "Huck Finn",
    "artist": "The Sign of the Southern Cross",
    "isrc": "FR33T0918602"
  },
  {
    "title": "Redneck Vikings from Hell",
    "artist": "Æther Realm",
    "isrc": "ATN262087801"
  },
  {
    "title": "Skeletons Tonight",
    "artist": "Thunderlip",
    "isrc": "USDLJ0500096"
  },
  {
    "title": "Carbon Shadows",
    "artist": "Gross Reality",
    "isrc": "QZNWW2396052"
  },
  {
    "title": "Losing My Religion",
    "artist": "The Reticent",
    "isrc": "ushm91238005"
  },
  {
    "title": "Be My Blood",
    "artist": "Young And In The Way",
    "isrc": "QZHNA1968189"
  },
  {
    "title": "A Very Calculating Snake",
    "artist": "The Demonstration",
    "isrc": "USFK90800119"
  },
  {
    "title": "Bearer of the Curse",
    "artist": "Paezor",
    "isrc": "QZHN32186812"
  },
  {
    "title": "Evil and Right",
    "artist": "Bedowyn",
    "isrc": "USA2P1339668"
  },
  {
    "title": "Push It to the Limit",
    "artist": "Salvación",
    "isrc": "usdy41577106"
  },
  {
    "title": "Inception",
    "artist": "Black Ritual",
    "isrc": "QZ22B1753328"
  },
  {
    "title": "Dissociation",
    "artist": "Written in Gray",
    "isrc": "SE6HN2029969"
  }
]