[
  {
    "title": "Give Up",
    "artist": "Mimi Mars, Darassa",
    "isrc": "TCAHO2370178"
  },
  {
    "title": "Dharau",
    "artist": "Ibraah, Harmonize",
    "isrc": "ESA122438933"
  },
  {
    "title": "Napendwa",
    "artist": "Kusah",
    "isrc": "TZA1X2200495"
  },
  {
    "title": "Niteme",
    "artist": "Whozu",
    "isrc": "USUYG1524074"
  },
  {
    "title": "Je T Aime",
    "artist": "Beka Flavour",
    "isrc": "AEA2W2494774"
  },
  {
    "title": "Baishoo",
    "artist": "Kayumba",
    "isrc": "FRX872189237"
  },
  {
    "title": "Ngarenaro",
    "artist": "Dogo Janja",
    "isrc": "CA5KR1919751"
  },
  {
    "title": "Nakuja (feat. Marioo)",
    "artist": "Tommy Flavour, Marioo",
    "isrc": "ZA41S2300123"
  },
  {
    "title": "Show Off",
    "artist": "Ben Pol, Darassa",
    "isrc": "TCAHS2317358"
  },
  {
    "title": "Madanga Ya Mke Wangu",
    "artist": "Meja Kunta, D Voice",
    "isrc": "TZA1X2100016"
  },
  {
    "title": "Dah! (feat. Alikiba)",
    "artist": "Nandy, Alikiba",
    "isrc": "ZA40S2400221"
  },
  {
    "title": "Star",
    "artist": "MABANTU",
    "isrc": "QZHZ42238501"
  },
  {
    "title": "Niwaze",
    "artist": "Ruby Afrika, The Mafik",
    "isrc": "TZA1X2000514"
  },
  {
    "title": "Puuh",
    "artist": "Billnass, Jay Melody",
    "isrc": "TZA1X2201195"
  },
  {
    "title": "Kioo",
    "artist": "Anjella, Harmonize",
    "isrc": "ZA41S2224347"
  },
  {
    "title": "Kiss Me",
    "artist": "Maua Sama",
    "isrc": "ZA41S2303913"
  },
  {
    "title": "Nibusu (feat. Yammi)",
    "artist": "Barnaba, Yammi",
    "isrc": "ZA40S2400843"
  },
  {
    "title": "You (feat. Yammi)",
    "artist": "AbduKiba, Yammi",
    "isrc": "ZA41S2304766"
  },
  {
    "title": "Me N You",
    "artist": "Ommy Dimpoz",
    "isrc": "ZA41S1447863"
  },
  {
    "title": "Kerewa",
    "artist": "Shetta, Diamond Platnumz",
    "isrc": "TZA1X2100184"
  },
  {
    "title": "Kibango (feat. Diamond Platnumz)",
    "artist": "Lava Lava, Diamond Platnumz",
    "isrc": "ZA40S2400780"
  },
  {
    "title": "Siku Hazigandi",
    "artist": "Lady Jaydee",
    "isrc": "USCGJ1270672"
  },
  {
    "title": "Ukinichiti",
    "artist": "Mac Voice",
    "isrc": "TCAGS2355340"
  },
  {
    "title": "Ni Wewe",
    "artist": "Killy Tz, Harmonize",
    "isrc": "ZA41S2101764"
  },
  {
    "title": "Siachani Nawe",
    "artist": "Barakah The Prince",
    "isrc": "TZA1X2200582"
  },
  {
    "title": "Ivo Ivo",
    "artist": "Baddest 47",
    "isrc": "TZA1X2200086"
  },
  {
    "title": "Ananipenda (feat. Soge Culebra, Marioo) - Remix",
    "artist": "Platform, Peipper, Gino Mella, Marioo, Soge Culebra",
    "isrc": "ZA56E2415566"
  },
  {
    "title": "We Endelea Tu",
    "artist": "MwanaFA",
    "isrc": "TZA1X2300198"
  },
  {
    "title": "Nobody but Me (feat. K.O)",
    "artist": "Vanessa Mdee, K.O",
    "isrc": "ZA56E1702945"
  },
  {
    "title": "Tetema (feat. Diamond Platnumz)",
    "artist": "Rayvanny, Diamond Platnumz",
    "isrc": "TCAFJ2126469"
  },
  {
    "title": "Ibaki Story",
    "artist": "Rich Mavoko",
    "isrc": "TCADJ1789984"
  },
  {
    "title": "Huu Mwaka",
    "artist": "Dayoo, Rayvanny",
    "isrc": "ZA41S2400090"
  },
  {
    "title": "Enjoy",
    "artist": "Jux, Diamond Platnumz",
    "isrc": "ZA56E2303708"
  },
  {
    "title": "Baba",
    "artist": "Stamina Shorwebwenzi, PROFESSOR JAY, One Six",
    "isrc": "TZA1X2100007"
  },
  {
    "title": "Inauma",
    "artist": "Aslay",
    "isrc": "TZA1X2200333"
  },
  {
    "title": "Lonely (feat. Nandy)",
    "artist": "Yammi, Nandy",
    "isrc": "ZA40S2400999"
  },
  {
    "title": "Single Again",
    "artist": "Harmonize",
    "isrc": "ZA41S2226940"
  },
  {
    "title": "Manu (feat. Jay Melody)",
    "artist": "Phina, Jay Melody",
    "isrc": "ZA41S2304703"
  },
  {
    "title": "Formula (Moto Zimelia)",
    "artist": "Joh Makini, Jay Melody, Bien",
    "isrc": "QZS7J2372345"
  },
  {
    "title": "Inde",
    "artist": "Dully Sykes, Harmonize",
    "isrc": "TZA1X2300577"
  },
  {
    "title": "Stupid",
    "artist": "Young Lunya, Khaligraph Jones",
    "isrc": "KEA842300028"
  },
  {
    "title": "Nakupenda",
    "artist": "Jay Melody",
    "isrc": "QZS7J2225279"
  },
  {
    "title": "Star",
    "artist": "Gigy Money, Chino Kidd",
    "isrc": "TZA1X2300654"
  },
  {
    "title": "Jini Kisirani",
    "artist": "Amber Lulu",
    "isrc": "TZA1X2100195"
  },
  {
    "title": "Amawele",
    "artist": "Marioo, TYLA, Ch'cco",
    "isrc": "ZA56E2201573"
  },
  {
    "title": "No Body (feat. Bien)",
    "artist": "Darassa, Bien",
    "isrc": "ZA41S2300235"
  },
  {
    "title": "Champion",
    "artist": "Kontawa, Nay Wamitego",
    "isrc": "QZS7J2236090"
  },
  {
    "title": "Mi Nawe",
    "artist": "Mocco Genius",
    "isrc": "ZA41S2304124"
  },
  {
    "title": "Rangi Rangi",
    "artist": "K2ga",
    "isrc": "ZA41S2224646"
  },
  {
    "title": "Shetani (feat. Costa Titch & Alfa Kat)",
    "artist": "Mbosso, Alfa Kat, Costa Titch",
    "isrc": "ZA41S2226329"
  },
  {
    "title": "Mkombozi",
    "artist": "Roma Mkatoliki, One Six",
    "isrc": "TZA1X2000841"
  },
  {
    "title": "Cheers",
    "artist": "Msodoki Young Killer, Colé Miss London",
    "isrc": "DGA0P2303525"
  },
  {
    "title": "Huku",
    "artist": "Alikiba, Tommy Flavour",
    "isrc": "ZA41S2302145"
  },
  {
    "title": "Low",
    "artist": "Rapcha",
    "isrc": "TZA3X2400002"
  },
  {
    "title": "Bachela",
    "artist": "Nay Wa Mitego",
    "isrc": "QZTLA2424899"
  },
  {
    "title": "Sina Kitete",
    "artist": "Mwasiti, Baddest 47",
    "isrc": "TZA272100022"
  },
  {
    "title": "Poa",
    "artist": "Country Wizzy, Marioo",
    "isrc": "QZMER2204180"
  },
  {
    "title": "Zawadi (feat. Dadiposlim)",
    "artist": "Zuchu, Dadiposlim",
    "isrc": "ZA40S2400275"
  },
  {
    "title": "Kilegeze",
    "artist": "Linah, Dogo Janja",
    "isrc": "TZA1X2000615"
  },
  {
    "title": "Kubali",
    "artist": "Lody Music",
    "isrc": "TCAFT2161103"
  },
  {
    "title": "Pita Huku",
    "artist": "Dulla Makabila",
    "isrc": "QZSYP2306975"
  },
  {
    "title": "Never Mind",
    "artist": "Vanillah, Roma Mkatoliki",
    "isrc": "QZK6L2487592"
  },
  {
    "title": "Neila",
    "artist": "Tunda Man, Chidi Benz",
    "isrc": "QZNJX2265038"
  },
  {
    "title": "Zoba",
    "artist": "D Voice",
    "isrc": "TCAIC2495169"
  },
  {
    "title": "Andazi",
    "artist": "Lulu Diva, Rayvanny, Chino Kidd, Whozu",
    "isrc": "QZSYP2357573"
  },
  {
    "title": "Yesa",
    "artist": "Chino Kidd, Jaivah, Marioo, Ma Gang",
    "isrc": "QZNJX2332571"
  },
  {
    "title": "Shemeji Yako",
    "artist": "Mzee wa Bwax, Mbosso",
    "isrc": "TCAHR2347555"
  },
  {
    "title": "Lala",
    "artist": "B2k Mnyama, Vanillah",
    "isrc": "QZTVM2315392"
  },
  {
    "title": "Haiwezekani",
    "artist": "Kassim Mganga",
    "isrc": "TZA1X2300032"
  },
  {
    "title": "Sitaki Mazoea",
    "artist": "Shilole, Jay Melody",
    "isrc": "TZA1X2200493"
  },
  {
    "title": "Nakuja - Remix",
    "artist": "Balaa MC, Marioo",
    "isrc": "FRS182088989"
  },
  {
    "title": "Amen",
    "artist": "Baba Levo, Diamond Platnumz",
    "isrc": "QZS7J2358177"
  },
  {
    "title": "Pi Pii",
    "artist": "Marlaw",
    "isrc": "ZA41S1411830"
  },
  {
    "title": "Basupa",
    "artist": "Young DareSalama, Dj ally B",
    "isrc": "QZNWU2350436"
  },
  {
    "title": "Antonia (feat. Harmonize)",
    "artist": "Abbah, Harmonize",
    "isrc": "ZA56E2100167"
  },
  {
    "title": "Lost In Love",
    "artist": "Dj Seven Worldwide, Singah, Bruce Melodie",
    "isrc": "QM4TX2351551"
  },
  {
    "title": "Mapenzi (feat. Barnaba)",
    "artist": "Nedy Music, Barnaba",
    "isrc": "ZA40S2400267"
  },
  {
    "title": "Bembea",
    "artist": "Aslay, Alikiba",
    "isrc": "FR96X1935369"
  },
  {
    "title": "Wandia",
    "artist": "Cheed",
    "isrc": "ZA41S2101936"
  },
  {
    "title": "Buruda",
    "artist": "Jaivah, Marioo",
    "isrc": "QMFMG2304454"
  },
  {
    "title": "Basi",
    "artist": "Yamoto Band",
    "isrc": "FR59R1711299"
  },
  {
    "title": "Tunaanza Na Mungu",
    "artist": "The Mafik",
    "isrc": "QZS7J2314689"
  },
  {
    "title": "Shu! (feat. Chley)",
    "artist": "Diamond Platnumz, Chley",
    "isrc": "ZA41S2301817"
  },
  {
    "title": "Corona Basi",
    "artist": "Hamadai, Christina Shusho, Beka Flavour, Kayumba, Marissa, Dogo Janja, Tommy Flavour, Young Lunya, Whozu, Saraphina, Jay Melody, Rapcha, Mr. Blue, Adam Mchomvu, Jesca Mshana, Stamina Shorwebwenzi, Kala Jeremiah, Nandy, Joh Makini, Lord Eyez",
    "isrc": "TZA1X2100593"
  },
  {
    "title": "Wewe hapoo",
    "artist": "Lony Bway, Marioo",
    "isrc": "QZRP52387202"
  },
  {
    "title": "Nani?",
    "artist": "Abigail Chams, Marioo",
    "isrc": "KEA842300001"
  },
  {
    "title": "Sina Raha",
    "artist": "Sam Wa Ukweli",
    "isrc": "SE6A91827640"
  },
  {
    "title": "Wapambe",
    "artist": "Haitham Kim, Barnaba",
    "isrc": "TZA1X2300748"
  },
  {
    "title": "Sina Ubaya",
    "artist": "Watu Fresh",
    "isrc": "QZTV32316704"
  },
  {
    "title": "Dakika Moja",
    "artist": "Ruby",
    "isrc": "FR59R1954974"
  },
  {
    "title": "Tit For Tat - Remix",
    "artist": "Rilvin, Billnass",
    "isrc": "TZA1X2100822"
  },
  {
    "title": "Bembeleza",
    "artist": "Quick Rocka, Joh Makini",
    "isrc": "TZA1X2000840"
  },
  {
    "title": "Wali Nazi",
    "artist": "Q Chief, TID",
    "isrc": "TZA1X2300901"
  },
  {
    "title": "Mapenzi au Pesa",
    "artist": "Centano",
    "isrc": "QZPYN2262614"
  },
  {
    "title": "Tunashine",
    "artist": "P-Funk Majani, Rapcha, Conboi Cannabino",
    "isrc": "QZGLM2337929"
  },
  {
    "title": "Nitazoea",
    "artist": "Hanstone",
    "isrc": "DGA0R2324389"
  },
  {
    "title": "Chawa",
    "artist": "Seneta Kilaka",
    "isrc": "TZA1X2200046"
  },
  {
    "title": "Niko Bize",
    "artist": "Xouh",
    "isrc": "QZW9L2334616"
  },
  {
    "title": "Pumzika (feat. Abela)",
    "artist": "Naomisia, Abela",
    "isrc": "USUYG1352727"
  },
  {
    "title": "Yeye",
    "artist": "GENIUSJINI X66",
    "isrc": "QZS7J2395547"
  },
  {
    "title": "Kamzozo",
    "artist": "Rosa Ree, G Nako",
    "isrc": "QMFMF2356827"
  },
  {
    "title": "Mtoto Wa Mtu",
    "artist": "Tamimu, Kayumba",
    "isrc": "QZQAY2202768"
  },
  {
    "title": "Boss",
    "artist": "LUKAMBA",
    "isrc": "TCAGR2256112"
  },
  {
    "title": "Wakalishe",
    "artist": "Gosby",
    "isrc": "QZFZ72069240"
  },
  {
    "title": "Sijui Nikoje",
    "artist": "Whozu",
    "isrc": "ZA41S2224809"
  },
  {
    "title": "We Don't Care",
    "artist": "Rj The Dj, Rayvanny, Meddy",
    "isrc": "TCAFC2040005"
  },
  {
    "title": "Pakua",
    "artist": "Jovial, Mejja",
    "isrc": "QZK6H2078328"
  },
  {
    "title": "Ghetto",
    "artist": "Sholo Mwamba",
    "isrc": "FRX201785721"
  },
  {
    "title": "Do Do",
    "artist": "Fabi",
    "isrc": "QZDA42391795"
  },
  {
    "title": "Restart",
    "artist": "Tofa Jaxx",
    "isrc": "DEYV52100054"
  },
  {
    "title": "Moyo Wangu",
    "artist": "Micky Singer, Maua Sama",
    "isrc": "TZA1X2300266"
  },
  {
    "title": "Nakuachaje",
    "artist": "Malkia Karen",
    "isrc": "US7VG2479145"
  },
  {
    "title": "Hainaga Ushemeji",
    "artist": "Man Fongo",
    "isrc": "TZA1X2100446"
  },
  {
    "title": "Namficha",
    "artist": "Joozey, Harmonize",
    "isrc": "QZGLM2395922"
  },
  {
    "title": "Utamu",
    "artist": "Salma Munde",
    "isrc": "ushm92088065"
  },
  {
    "title": "SOGEA SOGEA",
    "artist": "Ray C",
    "isrc": "QZNWS2298045"
  },
  {
    "title": "You",
    "artist": "Bruce africa",
    "isrc": "QZW9M2281411"
  },
  {
    "title": "Watu Feki",
    "artist": "Appy",
    "isrc": "QZNWW2362564"
  },
  {
    "title": "Ndembe Ndembe",
    "artist": "Bytar Beast, Marioo, Jaivah",
    "isrc": "ZA56E2304360"
  },
  {
    "title": "Vaileti",
    "artist": "Matonya",
    "isrc": "TZA1X2300056"
  },
  {
    "title": "Cigarette",
    "artist": "Turunesh",
    "isrc": "QZK6H2182745"
  },
  {
    "title": "Hujambo Mwanagu",
    "artist": "Rostam, Ferooz",
    "isrc": "TZA1X2100331"
  },
  {
    "title": "Kijuso (feat. Rayvanny)",
    "artist": "Queen Darleen, Rayvanny",
    "isrc": "TCADJ1752451"
  },
  {
    "title": "Noma Mwanangu",
    "artist": "P Mawenge, Deddy",
    "isrc": "QZDA82275139"
  },
  {
    "title": "Mapenzi Kizunguzungu",
    "artist": "Saida Karoli",
    "isrc": "TCAHK2375760"
  },
  {
    "title": "Popote",
    "artist": "Ronze",
    "isrc": "QZHN42317135"
  },
  {
    "title": "Jambo Jambo",
    "artist": "Steve Rnb",
    "isrc": "TZA1X2000929"
  },
  {
    "title": "Sir God",
    "artist": "Bando MC, Daway",
    "isrc": "TZA1X2300880"
  },
  {
    "title": "Nilipize",
    "artist": "Ibrah Nation",
    "isrc": "QZAMM2064096"
  },
  {
    "title": "Jike Shupa",
    "artist": "Nuh Mziwanda, Alikiba",
    "isrc": "TZA1X2201007"
  },
  {
    "title": "BamBam",
    "artist": "DVoice",
    "isrc": "QZZ972343388"
  },
  {
    "title": "Mapopo",
    "artist": "Damian Soul",
    "isrc": "TZA1X2001326"
  },
  {
    "title": "Wewe",
    "artist": "Hamisa Mobetto, Otile Brown",
    "isrc": "TCAGF2272689"
  },
  {
    "title": "Nionyeshe",
    "artist": "Q Chilla, Harmonize",
    "isrc": "ZA41S2100859"
  },
  {
    "title": "Roga Roga",
    "artist": "Ray C",
    "isrc": "TCADX1886916"
  },
  {
    "title": "Oya Oya Oya",
    "artist": "Mim Suleiman",
    "isrc": "TCACI1522775"
  },
  {
    "title": "Mbele Kwa Mbele",
    "artist": "Otuck William, Joh Makini",
    "isrc": "TCAFC2006444"
  },
  {
    "title": "Handsome",
    "artist": "Prince Dully Sykes",
    "isrc": "DECQ10600406"
  },
  {
    "title": "Deko",
    "artist": "Titok.O, Dully Sykes",
    "isrc": "QZK6M1901871"
  },
  {
    "title": "Pole",
    "artist": "Mimi Mars, Nandy",
    "isrc": "TCAHM2324822"
  },
  {
    "title": "I Wish",
    "artist": "Kusah",
    "isrc": "TZA1X2100790"
  },
  {
    "title": "Nitachelewa",
    "artist": "Ibraah",
    "isrc": "FRX762046234"
  },
  {
    "title": "Vavayo",
    "artist": "Whozu, Marioo",
    "isrc": "QZTLA2333492"
  },
  {
    "title": "Nakupenda",
    "artist": "Beka Flavour",
    "isrc": "QZ5AB2405302"
  },
  {
    "title": "Mama",
    "artist": "Kayumba",
    "isrc": "QZNJX2206940"
  },
  {
    "title": "Kilimanjaro (feat. Loui)",
    "artist": "Dogo Janja, Loui",
    "isrc": "ZA41S2304481"
  },
  {
    "title": "Huku",
    "artist": "Tommy Flavour, Alikiba, Iyanya",
    "isrc": "ZA40S2400452"
  },
  {
    "title": "Napenda Nipate Lau Nafasi",
    "artist": "Ben Pol",
    "isrc": "TCAEP2085713"
  },
  {
    "title": "Demu Wangu",
    "artist": "Meja Kunta, MABANTU",
    "isrc": "TZA1X2201178"
  },
  {
    "title": "Leo",
    "artist": "MABANTU, Marioo",
    "isrc": "QZNJZ2256929"
  },
  {
    "title": "Dah!",
    "artist": "Nandy",
    "isrc": "ZA41S2405415"
  },
  {
    "title": "Nadondosha",
    "artist": "Ruby Afrika, Kusah",
    "isrc": "TZA1X2000729"
  },
  {
    "title": "Toroka",
    "artist": "Anjella, Harmonize",
    "isrc": "ZA41S2102769"
  },
  {
    "title": "Zamani",
    "artist": "Maua Sama",
    "isrc": "ZA40S2400326"
  },
  {
    "title": "Number one",
    "artist": "Billnass, Mbosso",
    "isrc": "QZS7J2495002"
  },
  {
    "title": "Hadithi (feat. Diamond Platnumz)",
    "artist": "Barnaba, Diamond Platnumz",
    "isrc": "ZA41S2225005"
  },
  {
    "title": "Hainogi",
    "artist": "AbduKiba, Alikiba",
    "isrc": "QZNWY2138999"
  },
  {
    "title": "Namjua",
    "artist": "Shetta",
    "isrc": "TCACO1615004"
  },
  {
    "title": "Nai Nai",
    "artist": "Ommy Dimpoz",
    "isrc": "ZA41S1427884"
  },
  {
    "title": "Tajiri",
    "artist": "Lava Lava",
    "isrc": "ZA41S2301590"
  },
  {
    "title": "I Found Love",
    "artist": "Lady Jaydee, Rama Dee",
    "isrc": "QZTLA2334765"
  },
  {
    "title": "Nenda",
    "artist": "Mac Voice",
    "isrc": "TCAFU2104248"
  },
  {
    "title": "Bado",
    "artist": "Killy Tz",
    "isrc": "US7VG2493189"
  },
  {
    "title": "Sir God",
    "artist": "Baddest 47",
    "isrc": "TZA1X2200542"
  },
  {
    "title": "Niseme Nawe",
    "artist": "Barakah The Prince, Otile Brown",
    "isrc": "ZA41S1683062"
  },
  {
    "title": "Sio Kwa Ubaya",
    "artist": "MwanaFA, Harmonize",
    "isrc": "TZA1X2201183"
  },
  {
    "title": "Wololo",
    "artist": "Platform",
    "isrc": "ZA56E2415916"
  },
  {
    "title": "Juu (feat. Jux)",
    "artist": "Vanessa Mdee, Jux",
    "isrc": "ZA56E1702946"
  },
  {
    "title": "Sheri (feat. Fid Q)",
    "artist": "Rich Mavoko, Fid Q",
    "isrc": "TCADJ1718254"
  },
  {
    "title": "Zazazela (feat. Zaba)",
    "artist": "Rayvanny, Iyanya, ZiiBeats, Zaba",
    "isrc": "ZA40S2400717"
  },
  {
    "title": "Nikuone",
    "artist": "Dayoo",
    "isrc": "QZSR42110426"
  },
  {
    "title": "Machozi",
    "artist": "Stamina Shorwebwenzi, Bushoke",
    "isrc": "TZA1X2300119"
  },
  {
    "title": "Likizo",
    "artist": "Aslay",
    "isrc": "CA5KR1574796"
  },
  {
    "title": "Nisiulizwe",
    "artist": "Jux",
    "isrc": "ZA56E2415647"
  },
  {
    "title": "Tiririka",
    "artist": "Yammi",
    "isrc": "ZA41S2301399"
  },
  {
    "title": "Sisi Ni Wale",
    "artist": "Phina",
    "isrc": "ZA41S2304030"
  },
  {
    "title": "Bobea",
    "artist": "Joh Makini",
    "isrc": "TZA1X2300402"
  },
  {
    "title": "Single Again (Remix) [feat. Nkosazana Daughter]",
    "artist": "Harmonize, Nkosazana Daughter",
    "isrc": "ZA41S2304565"
  },
  {
    "title": "Utamu",
    "artist": "Dully Sykes, Ommy Dimpoz, Diamond Platnumz",
    "isrc": "ZA56E1516295"
  },
  {
    "title": "(Freestyle) Sessions 6",
    "artist": "Young Lunya",
    "isrc": "QZS652419778"
  },
  {
    "title": "Papa",
    "artist": "Gigy Money",
    "isrc": "TZA1X2000226"
  },
  {
    "title": "Sawa",
    "artist": "Jay Melody",
    "isrc": "QZTLA2334437"
  },
  {
    "title": "Unaiweka",
    "artist": "Amber Lulu",
    "isrc": "TZA1X2300763"
  },
  {
    "title": "Hakuna Matata",
    "artist": "Marioo",
    "isrc": "ZA56E2415856"
  },
  {
    "title": "Mbala Mwezi",
    "artist": "Kontawa, Jay Melody",
    "isrc": "QZQAY2375278"
  },
  {
    "title": "Romeo (feat. Zuchu)",
    "artist": "Darassa, Zuchu",
    "isrc": "ZA40S2400310"
  },
  {
    "title": "Mchuchu (feat. Alikiba)",
    "artist": "Mocco Genius, Alikiba",
    "isrc": "ZA40S2400697"
  },
  {
    "title": "Deep In Love",
    "artist": "K2ga",
    "isrc": "ZA41S2304822"
  },
  {
    "title": "Amepotea",
    "artist": "Mbosso",
    "isrc": "ZA41S2301340"
  },
  {
    "title": "Nasikia Harufu",
    "artist": "Roma Mkatoliki, Chid Benz",
    "isrc": "QZTLA2437274"
  },
  {
    "title": "A New Girlfriend Story",
    "artist": "Msodoki Young Killer",
    "isrc": "FR59R2018832"
  },
  {
    "title": "Mahaba",
    "artist": "Alikiba",
    "isrc": "ZA41S2300183"
  },
  {
    "title": "Unaua Vibe",
    "artist": "Rapcha, Young Lunya, Dwin",
    "isrc": "QMDA62128971"
  },
  {
    "title": "Mbele Kwa Mbele",
    "artist": "Nay Wa Mitego",
    "isrc": "FR59R1940471"
  },
  {
    "title": "Nalivua Pendo",
    "artist": "Mwasiti",
    "isrc": "TZA1X2000903"
  },
  {
    "title": "Baby",
    "artist": "Country Wizzy",
    "isrc": "QZNWT2246771"
  },
  {
    "title": "Koleza",
    "artist": "Linah",
    "isrc": "TZA1X2000556"
  },
  {
    "title": "Utaniua",
    "artist": "Zuchu",
    "isrc": "ZA41S2300174"
  },
  {
    "title": "Forever",
    "artist": "Lody Music, Nandy",
    "isrc": "QZGLM2304353"
  },
  {
    "title": "Ujaulamba",
    "artist": "Dulla Makabila",
    "isrc": "FR59R1940440"
  },
  {
    "title": "Sijazoea",
    "artist": "Vanillah",
    "isrc": "QZFZ32446552"
  },
  {
    "title": "Badman",
    "artist": "Tunda Man, Harmonize",
    "isrc": "QZHZ62238386"
  },
  {
    "title": "Kuachana Shingapi (Remix)",
    "artist": "D Voice, Platform, Lody Music, Barnaba",
    "isrc": "QZQAY2259286"
  },
  {
    "title": "Ona",
    "artist": "Lulu Diva, Rich Mavoko",
    "isrc": "TCADQ1847573"
  },
  {
    "title": "Koko",
    "artist": "Chino Kidd, Loui, Dj Kidlax",
    "isrc": "QZGLS2384761"
  },
  {
    "title": "Nampakia Mkongo",
    "artist": "Mzee wa Bwax, Elisha",
    "isrc": "TZA1X2201005"
  },
  {
    "title": "Mimi",
    "artist": "B2k Mnyama",
    "isrc": "QZW9M2338573"
  },
  {
    "title": "Subira",
    "artist": "Kassim Mganga, Christian Bella",
    "isrc": "ZA41S1449434"
  },
  {
    "title": "Ukintekenya",
    "artist": "Shilole, Aslay",
    "isrc": "TZA1X2000631"
  },
  {
    "title": "We Nani",
    "artist": "Balaa MC",
    "isrc": "FR96X2154739"
  },
  {
    "title": "Shusha",
    "artist": "Baba Levo, Diamond Platnumz",
    "isrc": "JMA272013970"
  },
  {
    "title": "Bembeleza",
    "artist": "Marlaw",
    "isrc": "ZA41S1411838"
  },
  {
    "title": "Mia",
    "artist": "Young DareSalama, Stamina Shorwebwenzi, Country Boy",
    "isrc": "TZA1X2000675"
  },
  {
    "title": "Mwagia Ndani (feat. Maua Sama and G Nako)",
    "artist": "Abbah, G Nako, Maua Sama",
    "isrc": "ZA56E2100176"
  },
  {
    "title": "Say Yes",
    "artist": "Dj Seven Worldwide, Harmonize",
    "isrc": "QM4TX2351568"
  },
  {
    "title": "One & Only",
    "artist": "Nedy Music, Ruby Afrika",
    "isrc": "TZA1X2000503"
  },
  {
    "title": "Moyo Kiburi",
    "artist": "Aslay",
    "isrc": "FR10S2067173"
  },
  {
    "title": "Simuachi",
    "artist": "Cheed",
    "isrc": "QZNJW2358090"
  },
  {
    "title": "Kautaka",
    "artist": "Jaivah, JFS Music, King Tone SA",
    "isrc": "QM6MZ2485056"
  },
  {
    "title": "Mama",
    "artist": "Yamoto Band",
    "isrc": "ZA41S1642341"
  },
  {
    "title": "Passenger",
    "artist": "The Mafik",
    "isrc": "TZA1X2000499"
  },
  {
    "title": "Niamini",
    "artist": "Hamadai, Alikiba",
    "isrc": "TZA1X2200207"
  },
  {
    "title": "Wewe Hapo",
    "artist": "Lony Bway",
    "isrc": "QZNWQ2348326"
  },
  {
    "title": "Komasava (Comment Ça Va)",
    "artist": "Diamond Platnumz, Khalil Harrison, Chley",
    "isrc": "ZA40S2400914"
  },
  {
    "title": "Milele",
    "artist": "Abigail Chams",
    "isrc": "KEA842300012"
  },
  {
    "title": "Hata Kwetu Wapo",
    "artist": "Sam Wa Ukweli",
    "isrc": "SE6A91827641"
  },
  {
    "title": "Ukaniumiza",
    "artist": "Haitham Kim, Dayoo",
    "isrc": "QZYXP2358114"
  },
  {
    "title": "Wololo",
    "artist": "Watu Fresh",
    "isrc": "GBWUL2382534"
  },
  {
    "title": "Bullet",
    "artist": "Quick Rocka, Q Jay",
    "isrc": "TZA1X2000601"
  },
  {
    "title": "Uhali Gani",
    "artist": "Q Chief",
    "isrc": "TZA1X2200686"
  },
  {
    "title": "Peke Yangu",
    "artist": "Centano",
    "isrc": "QZW9L2330818"
  },
  {
    "title": "BBM",
    "artist": "P-Funk Majani, Ngwair, Rapcha, Jay Melody",
    "isrc": "QZW9K2389044"
  },
  {
    "title": "Wenge",
    "artist": "Mimi Mars",
    "isrc": "TZA1X2100024"
  },
  {
    "title": "I Don't Care",
    "artist": "Kusah",
    "isrc": "TZA1X2101000"
  },
  {
    "title": "One Night Stand",
    "artist": "Ibraah, Harmonize",
    "isrc": "FR59R2033038"
  },
  {
    "title": "Ameyatimba - Remix",
    "artist": "Whozu, Billnass, Mbosso",
    "isrc": "QZS7J2319540"
  },
  {
    "title": "Sikinai",
    "artist": "Beka Flavour",
    "isrc": "TZA1X2000493"
  },
  {
    "title": "Umeniweza",
    "artist": "Kayumba, Linah",
    "isrc": "QZNJW2293991"
  },
  {
    "title": "Banana",
    "artist": "Dogo Janja",
    "isrc": "CA5KR1822631"
  },
  {
    "title": "Omukwano",
    "artist": "Tommy Flavour, Alikiba",
    "isrc": "FR2X42060439"
  },
  {
    "title": "I’m in Love",
    "artist": "Ben Pol, Phina",
    "isrc": "TCAHS2317389"
  },
  {
    "title": "HASSANI",
    "artist": "Meja Kunta",
    "isrc": "QMFMG2322212"
  },
  {
    "title": "Maokoto",
    "artist": "MABANTU, Navy Kenzo",
    "isrc": "QZNJY2397699"
  },
  {
    "title": "Na Enjoy (feat. Darassa)",
    "artist": "Ruby Afrika, Darassa",
    "isrc": "ZA56E2003258"
  },
  {
    "title": "Wahala",
    "artist": "Nandy, Khanyisa, ZiiBeats",
    "isrc": "ZA40S2400719"
  },
  {
    "title": "Kama",
    "artist": "Anjella, Harmonize",
    "isrc": "ZA41S2102649"
  },
  {
    "title": "Look At Me (feat. Darassa)",
    "artist": "Maua Sama, Darassa",
    "isrc": "ZA41S2304801"
  },
  {
    "title": "Bye",
    "artist": "Billnass, Nandy",
    "isrc": "TZA1X2200668"
  },
  {
    "title": "Marry Me (feat. Marioo)",
    "artist": "Barnaba, Marioo",
    "isrc": "ZA41S2225009"
  },
  {
    "title": "Muda (feat. Alikiba & Vanillah)",
    "artist": "AbduKiba, Alikiba, Vanillah",
    "isrc": "ZA41S2304596"
  },
  {
    "title": "Shikorobo",
    "artist": "Shetta, KCee",
    "isrc": "ZA41S1449565"
  },
  {
    "title": "Ni Wewe",
    "artist": "Ommy Dimpoz",
    "isrc": "ZA41S1908497"
  },
  {
    "title": "Siwema",
    "artist": "Lady Jaydee",
    "isrc": "TZA1X2000117"
  },
  {
    "title": "Tuna Kikao (feat. Diamond Platnumz)",
    "artist": "Lava Lava, Diamond Platnumz",
    "isrc": "ZA41S2301724"
  },
  {
    "title": "Tamu",
    "artist": "Mac Voice, Rayvanny",
    "isrc": "TCAFU2104264"
  },
  {
    "title": "Nihurumie",
    "artist": "Killy Tz",
    "isrc": "QZ5AB2387375"
  },
  {
    "title": "Zagamua",
    "artist": "Baddest 47, MABANTU",
    "isrc": "TZA1X2201044"
  },
  {
    "title": "Permanent Love",
    "artist": "Barakah The Prince, Joh Makini",
    "isrc": "TZA1X2200988"
  },
  {
    "title": "Yalaiti",
    "artist": "MwanaFA, Linah",
    "isrc": "TZA1X2300014"
  },
  {
    "title": "Ananipenda",
    "artist": "Platform, Marioo",
    "isrc": "ZA56E2302192"
  },
  {
    "title": "Kisela (feat. Mr. P)",
    "artist": "Vanessa Mdee, Mr. P",
    "isrc": "ZA56E1702930"
  },
  {
    "title": "Kokoro (feat. Diamond Platnumz)",
    "artist": "Rich Mavoko, Diamond Platnumz",
    "isrc": "TCADJ1755328"
  },
  {
    "title": "Weekend",
    "artist": "Dayoo",
    "isrc": "QZSYP2358341"
  },
  {
    "title": "Kabwela",
    "artist": "Stamina Shorwebwenzi, Rich Mavoko",
    "isrc": "TZA1X2000815"
  },
  {
    "title": "Nitongoze (feat. Diamond Platnumz)",
    "artist": "Rayvanny, Diamond Platnumz",
    "isrc": "ZA41S2226443"
  },
  {
    "title": "Pusha",
    "artist": "Aslay",
    "isrc": "CA5KR1574803"
  },
  {
    "title": "BADO",
    "artist": "Jux",
    "isrc": "ZA56E2415697"
  },
  {
    "title": "Love Crazy",
    "artist": "Yammi, Lexsil, ZiiBeats",
    "isrc": "ZA40S2400003"
  },
  {
    "title": "Nusu Nusu",
    "artist": "Joh Makini",
    "isrc": "TZA1X2000469"
  },
  {
    "title": "Wawili",
    "artist": "Phina",
    "isrc": "ZA40S2400276"
  },
  {
    "title": "Disconnect (feat. Marioo)",
    "artist": "Harmonize, Marioo",
    "isrc": "ZA40S2400574"
  },
  {
    "title": "Raha Ya Tunda",
    "artist": "Dully Sykes, Yammi, Young Lunya",
    "isrc": "TZA1X2300586"
  },
  {
    "title": "Wanene Studio Session",
    "artist": "Young Lunya",
    "isrc": "TZA1X2000925"
  },
  {
    "title": "Chizi",
    "artist": "Gigy Money, GENIUSJINI X66",
    "isrc": "TZA1X2300655"
  },
  {
    "title": "Nitasema",
    "artist": "Jay Melody",
    "isrc": "QZSYP2355765"
  },
  {
    "title": "Una Sh Ngapi",
    "artist": "Amber Lulu",
    "isrc": "TZA1X2100193"
  },
  {
    "title": "Mi Amor (feat. Jovial)",
    "artist": "Marioo, Jovial",
    "isrc": "ZA56E2102282"
  },
  {
    "title": "Sikuachi",
    "artist": "Kontawa, Maua Sama",
    "isrc": "QZQAY2319480"
  },
  {
    "title": "Kama Utanipenda",
    "artist": "Darassa, Rich Mavoko",
    "isrc": "FRX201652341"
  },
  {
    "title": "Hello",
    "artist": "Mocco Genius",
    "isrc": "ZA40S2400036"
  }
]