[
  {
    "title": "Ungodly Death",
    "artist": "Ascended Dead",
    "isrc": "USJE72318202"
  },
  {
    "title": "Purging Through Flesh",
    "artist": "Hyperdontia",
    "isrc": "QM6N21885866"
  },
  {
    "title": "Blood of Abomination",
    "artist": "Witch Vomit",
    "isrc": "USJE72419603"
  },
  {
    "title": "Eternal Procession",
    "artist": "Mortiferum",
    "isrc": "USN682126301"
  },
  {
    "title": "Indwelling Archon",
    "artist": "Vastum",
    "isrc": "QZTAW2316147"
  },
  {
    "title": "Efter obduktionen",
    "artist": "Undergang",
    "isrc": "QM6MZ1755968"
  },
  {
    "title": "Suffer Minutiae",
    "artist": "Contaminated",
    "isrc": "QMBZ92372239"
  },
  {
    "title": "Wretched Sons",
    "artist": "Diocletian",
    "isrc": "FR4E61401060"
  },
  {
    "title": "Regurgitated Communion",
    "artist": "Of Feather And Bone",
    "isrc": "USN682025201"
  },
  {
    "title": "Cut the Cord",
    "artist": "Necrot",
    "isrc": "QM4TW2438043"
  },
  {
    "title": "Festering Castration",
    "artist": "Torture Rack",
    "isrc": "USJE71810601"
  },
  {
    "title": "Black Vertebrae",
    "artist": "Teitanblood",
    "isrc": "FXQ111900028"
  },
  {
    "title": "The Perfect Memory (Phantasm of Aura)",
    "artist": "Tomb Mold",
    "isrc": "USJE72320001"
  },
  {
    "title": "Liquified Mind",
    "artist": "Outer Heaven",
    "isrc": "US2642348505"
  },
  {
    "title": "Voidspawn",
    "artist": "Chthe'ilist",
    "isrc": "USN681610003"
  },
  {
    "title": "Carve",
    "artist": "Mortuous",
    "isrc": "ushm82257570"
  },
  {
    "title": "To Raise the Writhing Shadows",
    "artist": "Ritual Necromancy",
    "isrc": "QM4TX1859660"
  },
  {
    "title": "The Blood of Mars",
    "artist": "Left Cross",
    "isrc": "USN682331002"
  },
  {
    "title": "Entomb",
    "artist": "Vermin Womb",
    "isrc": "USCHW1610301"
  },
  {
    "title": "Enigma Signals",
    "artist": "Altarage",
    "isrc": "UKXN22324307"
  },
  {
    "title": "Built on Wrought",
    "artist": "Innumerable Forms",
    "isrc": "USN682228502"
  },
  {
    "title": "Worship",
    "artist": "Faceless Burial",
    "isrc": "USA2Z2000746"
  },
  {
    "title": "Continuum Cruciatus",
    "artist": "Infernal Coil",
    "isrc": "USN681820502"
  },
  {
    "title": "Kadonneet jumalat",
    "artist": "Rippikoulu",
    "isrc": "DEZ651342480"
  },
  {
    "title": "Forged Doctrine",
    "artist": "Heresiarch",
    "isrc": "TCAHZ2485382"
  },
  {
    "title": "Righteous Fist to the Teeth of the Wicked",
    "artist": "Ripped to Shreds",
    "isrc": "QZFZ42084169"
  },
  {
    "title": "Devoured Death",
    "artist": "Incantation",
    "isrc": "US2640670102"
  },
  {
    "title": "Artificial Purgatory",
    "artist": "Our Place of Worship is Silence",
    "isrc": "USCHW1812501"
  },
  {
    "title": "Enjoyment of Annihilation",
    "artist": "Galvanizer",
    "isrc": "uscgj1811626"
  },
  {
    "title": "To See Death Just Once",
    "artist": "Ulcerate",
    "isrc": "FXQ732300087"
  },
  {
    "title": "Lecherous Molestation",
    "artist": "Impetuous Ritual",
    "isrc": "USN682230102"
  },
  {
    "title": "Conquered and Disposed",
    "artist": "Genocide Pact",
    "isrc": "US2641739301"
  },
  {
    "title": "World Without God",
    "artist": "Convulse",
    "isrc": "FI7S51800039"
  },
  {
    "title": "Deep Blue Darkness",
    "artist": "Purtenance",
    "isrc": "CH6542321125"
  },
  {
    "title": "Dissenting the Waking Shell",
    "artist": "Adversarial",
    "isrc": "QM7281591292"
  },
  {
    "title": "Solar Witch",
    "artist": "Thantifaxath",
    "isrc": "USA2Z2300549"
  },
  {
    "title": "Carnal Mutilation",
    "artist": "Anatomia",
    "isrc": "SE4U51502701"
  },
  {
    "title": "A Heart to Judge",
    "artist": "Aosoth",
    "isrc": "QM6P41761833"
  },
  {
    "title": "Twisted Visions of Creation",
    "artist": "Petrification",
    "isrc": "FI7S52300244"
  },
  {
    "title": "Usurpation",
    "artist": "Knelt Rote",
    "isrc": "QM4TW1726141"
  },
  {
    "title": "Your Prophetic Throne Of Ivory",
    "artist": "Disembowelment",
    "isrc": "DED830502802"
  },
  {
    "title": "Jesters of Recession",
    "artist": "Rottrevore",
    "isrc": "USI4R0911250"
  },
  {
    "title": "Plague Evockation (Pestilentiam Intus Vocamus, Voluntatem Absolvimus, Pt. 1)",
    "artist": "Mitochondrion",
    "isrc": "QZDA51905305"
  },
  {
    "title": "Death's Disciple",
    "artist": "Drawn And Quartered",
    "isrc": "QZHN62196027"
  },
  {
    "title": "Brutalist Imperator",
    "artist": "Nightmarer",
    "isrc": "QMEU32215920"
  },
  {
    "title": "Serpent Sun",
    "artist": "Nightbringer",
    "isrc": "FR33T1787608"
  },
  {
    "title": "Naught but Death",
    "artist": "Funeral Mist",
    "isrc": "QZ5FN1888247"
  },
  {
    "title": "Black Breath",
    "artist": "Repulsion",
    "isrc": "US2640356316"
  },
  {
    "title": "Hexahedron: Tilling the Human Soil",
    "artist": "Dodecahedron",
    "isrc": "FR33T1787303"
  },
  {
    "title": "Swarming Opulence - Redux 1924",
    "artist": "Imperial Triumphant",
    "isrc": "GBDHC2444801"
  },
  {
    "title": "Okeanos",
    "artist": "Succumb",
    "isrc": "USA2Z2100292"
  },
  {
    "title": "Trigrammaton",
    "artist": "Arkhon Infaustus",
    "isrc": "FR6V80703610"
  },
  {
    "title": "Vehement Decimation",
    "artist": "Pseudogod",
    "isrc": "US6R21304097"
  },
  {
    "title": "I Feel Nothing When You Cry",
    "artist": "Thou",
    "isrc": "US5NR2434205"
  },
  {
    "title": "Maruta",
    "artist": "Carnation",
    "isrc": "FR33T2376402"
  },
  {
    "title": "Worship the Crypt",
    "artist": "Noose Rot",
    "isrc": "USA2P1804754"
  },
  {
    "title": "De Gloria Martyrum Et Confessorum",
    "artist": "Autokrator",
    "isrc": "QZMEN2169006"
  },
  {
    "title": "Gestation Within the Lunar Miasmic Envelope",
    "artist": "Prosanctus Inferi",
    "isrc": "QM4TW1726120"
  },
  {
    "title": "Creation Myth",
    "artist": "Inexorum",
    "isrc": "USA2B2202207"
  },
  {
    "title": "Denial in Abstraction",
    "artist": "Construct of Lethe",
    "isrc": "QMEU32403767"
  },
  {
    "title": "Black Pyramid",
    "artist": "Mutilation Rites",
    "isrc": "USERN1008759"
  },
  {
    "title": "A Sunless Dawn",
    "artist": "Void Ritual",
    "isrc": "QZDA71876953"
  },
  {
    "title": "Where Nonexistence Is All",
    "artist": "Arthedain",
    "isrc": "UKCVA1801952"
  },
  {
    "title": "Indulging Psychotic Thoughts",
    "artist": "Depravity",
    "isrc": "QMEU32021516"
  },
  {
    "title": "Age of the Fanatics",
    "artist": "Gutter Instinct",
    "isrc": "USERN1009363"
  },
  {
    "title": "Mold Upheaval",
    "artist": "Atavisma",
    "isrc": "uscgh2028197"
  },
  {
    "title": "Crepuscular Crescendo",
    "artist": "Extremity",
    "isrc": "USJE71710010"
  },
  {
    "title": "Maximize Terror",
    "artist": "The Lion's Daughter",
    "isrc": "QZNWR2360862"
  },
  {
    "title": "The Ruin",
    "artist": "Ails",
    "isrc": "USA2Z1810269"
  },
  {
    "title": "Crush the Empire",
    "artist": "Axis Of Despair",
    "isrc": "USZPA0901691"
  },
  {
    "title": "Conquering Divinity",
    "artist": "Phrenelith",
    "isrc": "QM6MZ1755978"
  },
  {
    "title": "Nexus of the Black Flame",
    "artist": "Ascended Dead",
    "isrc": "USJE72318203"
  },
  {
    "title": "Nauseating Hallucinations",
    "artist": "Hyperdontia",
    "isrc": "GBHLW2300579"
  },
  {
    "title": "Endless Fall",
    "artist": "Witch Vomit",
    "isrc": "USJE72419602"
  },
  {
    "title": "Incubus of Bloodstained Visions",
    "artist": "Mortiferum",
    "isrc": "USN682126302"
  },
  {
    "title": "Amniosis",
    "artist": "Vastum",
    "isrc": "QZES91824341"
  },
  {
    "title": "Død",
    "artist": "Undergang",
    "isrc": "USA2Z2301298"
  },
  {
    "title": "Cosmic Shit Show",
    "artist": "Contaminated",
    "isrc": "QMBZ92372240"
  },
  {
    "title": "Entropic Self Immolation",
    "artist": "Of Feather And Bone",
    "isrc": "USN682025202"
  },
  {
    "title": "Traitor's Gallow",
    "artist": "Diocletian",
    "isrc": "FR4E61401080"
  },
  {
    "title": "Drill the Skull",
    "artist": "Necrot",
    "isrc": "QM4TW2438046"
  },
  {
    "title": "Decrepit Funeral Home",
    "artist": "Torture Rack",
    "isrc": "USJE72318402"
  },
  {
    "title": "Whore Mass",
    "artist": "Teitanblood",
    "isrc": "QZ5FN1864250"
  },
  {
    "title": "Will of Whispers",
    "artist": "Tomb Mold",
    "isrc": "USJE72320003"
  },
  {
    "title": "Pillars Of Dust",
    "artist": "Outer Heaven",
    "isrc": "US2642348502"
  },
  {
    "title": "Into the Vaults of Ingurgitating Obscurity",
    "artist": "Chthe'ilist",
    "isrc": "USN681610002"
  },
  {
    "title": "Metamorphosis",
    "artist": "Mortuous",
    "isrc": "ushm82257572"
  },
  {
    "title": "Command the Sigil",
    "artist": "Ritual Necromancy",
    "isrc": "QM4TX1859661"
  },
  {
    "title": "Deity of Molten Iron",
    "artist": "Left Cross",
    "isrc": "USN682331003"
  },
  {
    "title": "Industrialist",
    "artist": "Vermin Womb",
    "isrc": "USCHW1610302"
  },
  {
    "title": "Negative Arrival",
    "artist": "Altarage",
    "isrc": "FR33T2112201"
  },
  {
    "title": "The Fall Down",
    "artist": "Innumerable Forms",
    "isrc": "QZ2YP2322502"
  },
  {
    "title": "Equipoise Recast",
    "artist": "Faceless Burial",
    "isrc": "GBHLW2201922"
  },
  {
    "title": "Crusher of the Seed",
    "artist": "Infernal Coil",
    "isrc": "USN681820503"
  },
  {
    "title": "Kuolematon totuus",
    "artist": "Rippikoulu",
    "isrc": "DEZ651342481"
  },
  {
    "title": "Manifest Odium",
    "artist": "Heresiarch",
    "isrc": "TCAHZ2485401"
  },
  {
    "title": "Golgotha",
    "artist": "Incantation",
    "isrc": "US2640670101"
  },
  {
    "title": "Eight Immortals Feast",
    "artist": "Ripped to Shreds",
    "isrc": "QZFZ42084171"
  },
  {
    "title": "Labyrinth Disorientation",
    "artist": "Our Place of Worship is Silence",
    "isrc": "USCHW1812504"
  },
  {
    "title": "Mood for the Blade",
    "artist": "Galvanizer",
    "isrc": "uscgj1811625"
  },
  {
    "title": "Sanguinary Abstraction",
    "artist": "Impetuous Ritual",
    "isrc": "USN682230101"
  },
  {
    "title": "To Flow Through Ashen Hearts",
    "artist": "Ulcerate",
    "isrc": "FXQ732300083"
  },
  {
    "title": "Led to Extinction",
    "artist": "Genocide Pact",
    "isrc": "US2642148601"
  },
  {
    "title": "Putrid Intercourse",
    "artist": "Convulse",
    "isrc": "FI7S51800040"
  },
  {
    "title": "A Dark Cloud Arises",
    "artist": "Purtenance",
    "isrc": "CH6542321128"
  },
  {
    "title": "Immersion Void Paragon",
    "artist": "Adversarial",
    "isrc": "QM7281591294"
  },
  {
    "title": "The Lost Wisdom of Wolves",
    "artist": "Thantifaxath",
    "isrc": "USA2Z2300551"
  },
  {
    "title": "Dismemberment",
    "artist": "Anatomia",
    "isrc": "GBHLW2100990"
  },
  {
    "title": "Her Feet Upon the Earth, Blooming the Fruits of Blood",
    "artist": "Aosoth",
    "isrc": "QM6P41761834"
  },
  {
    "title": "Oneiric Obscurum",
    "artist": "Petrification",
    "isrc": "FI7S52300245"
  },
  {
    "title": "Hunger",
    "artist": "Knelt Rote",
    "isrc": "QM4TW1726142"
  },
  {
    "title": "Excoriate",
    "artist": "Disembowelment",
    "isrc": "US2640560403"
  },
  {
    "title": "Spawn of Ignorance",
    "artist": "Rottrevore",
    "isrc": "USI4R0911252"
  },
  {
    "title": "Into the Pit of Babel",
    "artist": "Mitochondrion",
    "isrc": "QZ8LD1914860"
  },
  {
    "title": "Nefarious Rites",
    "artist": "Drawn And Quartered",
    "isrc": "QZB4J1886836"
  },
  {
    "title": "Baptismal Tomb",
    "artist": "Nightmarer",
    "isrc": "QMEU32215921"
  },
  {
    "title": "As Wolves Amongst Ruins",
    "artist": "Nightbringer",
    "isrc": "FR33T1787601"
  },
  {
    "title": "Metamorphosis",
    "artist": "Funeral Mist",
    "isrc": "QZ5FN1888250"
  },
  {
    "title": "Radiation Sickness",
    "artist": "Repulsion",
    "isrc": "US2640356306"
  },
  {
    "title": "Tetrahedron: The Culling of the Unwanted from the Earth",
    "artist": "Dodecahedron",
    "isrc": "FR33T1787302"
  },
  {
    "title": "Lower World - Redux 1924",
    "artist": "Imperial Triumphant",
    "isrc": "GBDHC2444802"
  },
  {
    "title": "Bestial Vengeance",
    "artist": "Ascended Dead",
    "isrc": "USJE72318204"
  },
  {
    "title": "Degradations of the Flesh",
    "artist": "Hyperdontia",
    "isrc": "GBHLW2300581"
  },
  {
    "title": "Archaic Vision of Despair",
    "artist": "Mortiferum",
    "isrc": "USN681923101"
  },
  {
    "title": "Black Wings of Desolation",
    "artist": "Witch Vomit",
    "isrc": "USJE72419606"
  },
  {
    "title": "Priapic Chasms",
    "artist": "Vastum",
    "isrc": "QZTAW2316144"
  },
  {
    "title": "Klynget op i en galge af egne indvolde",
    "artist": "Undergang",
    "isrc": "QM6MZ1755970"
  },
  {
    "title": "Feral Demise",
    "artist": "Contaminated",
    "isrc": "QMBZ92372241"
  },
  {
    "title": "Repulsive Obscurity",
    "artist": "Of Feather And Bone",
    "isrc": "USN681819901"
  },
  {
    "title": "Summoning Fear",
    "artist": "Diocletian",
    "isrc": "FR4E61401070"
  },
  {
    "title": "Lifeless Birth",
    "artist": "Necrot",
    "isrc": "QM4TW2438044"
  },
  {
    "title": "Ceremonial Flesh Feast",
    "artist": "Torture Rack",
    "isrc": "USJE72318401"
  },
  {
    "title": "Anteinfierno",
    "artist": "Teitanblood",
    "isrc": "QZ5FN1863605"
  },
  {
    "title": "Angelic Fabrications",
    "artist": "Tomb Mold",
    "isrc": "USJE72320002"
  },
  {
    "title": "Soul Remnants",
    "artist": "Outer Heaven",
    "isrc": "US2642348501"
  },
  {
    "title": "Le Dernier Crépuscule",
    "artist": "Chthe'ilist",
    "isrc": "USN681610001"
  },
  {
    "title": "Nothing",
    "artist": "Mortuous",
    "isrc": "ushm82257571"
  },
  {
    "title": "Discarnate Machination",
    "artist": "Ritual Necromancy",
    "isrc": "QM4TX1859662"
  },
  {
    "title": "Burning Raids",
    "artist": "Left Cross",
    "isrc": "USN682331004"
  },
  {
    "title": "Gamnique (Cold World)",
    "artist": "Vermin Womb",
    "isrc": "QM4TX2228519"
  },
  {
    "title": "Magno Evento",
    "artist": "Altarage",
    "isrc": "FR33T2112202"
  },
  {
    "title": "Philosophical Collapse",
    "artist": "Innumerable Forms",
    "isrc": "USN682228501"
  },
  {
    "title": "Seeping Aberrational Fissures",
    "artist": "Faceless Burial",
    "isrc": "QZ2YP1710502"
  },
  {
    "title": "49 Suns",
    "artist": "Infernal Coil",
    "isrc": "USN681820504"
  },
  {
    "title": "Ikuinen piina",
    "artist": "Rippikoulu",
    "isrc": "DEZ651342482"
  },
  {
    "title": "Noose Above the Abyss",
    "artist": "Heresiarch",
    "isrc": "TCAHZ2405539"
  }
]