[
  {
    "preview_url": "https://p.scdn.co/mp3-preview/af20d36fdfc0a5abdc4390a67077323a2098ea76",
    "preview_title": "I Virtuosi Italiani - Concerto for Trumpet, Strings and Percussion in B-Flat Major: I. Allegro"
  },
  {
    "preview_url": "https://p.scdn.co/mp3-preview/09936d4cadbfb8e9d77ad2706acc2c974fdffd96",
    "preview_title": "Metamorphose String Orchestra - Pavane pour une infante défunte"
  },
  {
    "preview_url": "https://p.scdn.co/mp3-preview/c997992395a2bc101241798d2d3a3e313b38a8d2",
    "preview_title": "I Musici - Brandenburg Concerto No. 2 in F, BWV 1047: 1. (Allegro)"
  },
  {
    "preview_url": "https://p.scdn.co/mp3-preview/650096ef9fbbbde52a0b75d016cc14f1334d22d7",
    "preview_title": "Amsterdam Sinfonietta - Sinfonia No. 2 in D Major, MWV N2: I. Allegro"
  },
  {
    "preview_url": "https://p.scdn.co/mp3-preview/781e66316aeba827b244815631ec729ad5c04aa6",
    "preview_title": "12 Ensemble - The Lamb"
  },
  {
    "preview_url": "https://p.scdn.co/mp3-preview/eab00e0dbe8c9c0dc0eb11ca9bc885f16d27282f",
    "preview_title": "Budapest Strings - Solomon, HWV 67, Act III: Sinfonia, \"Arrival of the Queen of Sheba\""
  },
  {
    "preview_url": "https://p.scdn.co/mp3-preview/c4c3c7a3015fc5ec5b588c5fc0e6c2e4136c1b85",
    "preview_title": "TrondheimSolistene - MAGNIFICAT: VI. Suscepit Israel"
  },
  {
    "preview_url": "https://p.scdn.co/mp3-preview/003f8bcb656c43bcd1410eecc32ceb1c853fd92e",
    "preview_title": "Lucerne Festival Strings - Ciacona In G Minor"
  },
  {
    "preview_url": "https://p.scdn.co/mp3-preview/904e172bb7a03bbf9d7e3e89298683ea05fb96d8",
    "preview_title": "Moscow Soloists - Serenade for Strings in C major, Op. 48: IV. Finale (Tema russo): Andante - Allegro con spirito"
  },
  {
    "preview_url": "https://p.scdn.co/mp3-preview/ea4fe0b2aeee708b400bd9a9efc801465cf9e55d",
    "preview_title": "Ensemble Resonanz - Symphony No. 36 in C major, K. 425 \"Linz\": IV. Presto"
  },
  {
    "preview_url": "https://p.scdn.co/mp3-preview/839154f53d4c95398db8e2922cba789a5d3851c5",
    "preview_title": "Munich Chamber Orchestra - Dance Of The Blessed Spirits"
  },
  {
    "preview_url": "https://p.scdn.co/mp3-preview/dbbb55021f18ecf514af242ac84fbd7f619e0800",
    "preview_title": "Royal Stockholm Philharmonic Orchestra Strings - Bergakungen (The Mountain King) Suite: IV. Vlallflickans dans (Herdmaiden's Dance)"
  },
  {
    "preview_url": "https://p.scdn.co/mp3-preview/bc0ddba49d57ceb55ea83885207be87d6ee706ec",
    "preview_title": "Camerata Bern - Serenade No. 13 in G Major, K. 525 \"Eine kleine Nachtmusik\": I. Allegro"
  },
  {
    "preview_url": "https://p.scdn.co/mp3-preview/115462c67244fbacf855e8702ef49ccba9d8a28a",
    "preview_title": "Metamorphosen Berlin - Palladio: I. Allegretto"
  },
  {
    "preview_url": "https://p.scdn.co/mp3-preview/d39bfddbfb30ba7deb747bdc9bb827a07a0178cd",
    "preview_title": "English String Orchestra - A Downland Suite: III. Minuet"
  },
  {
    "preview_url": "https://p.scdn.co/mp3-preview/1eeb6fd739b189b7ae7db19c8d6430b7395bd4bd",
    "preview_title": "The Russian Virtuosi of Europe - Serenade for String Orchestra in C Major, Op. 48, TH 48: II. Valse"
  },
  {
    "preview_url": "https://p.scdn.co/mp3-preview/24c23460c26176d16dae2cf15e76d1c671f8e467",
    "preview_title": "The Helsinki Strings - Sibelius: Andante festivo"
  },
  {
    "preview_url": "https://p.scdn.co/mp3-preview/38b53cbd08d1781a5b90a33b24fd94ccb46c7960",
    "preview_title": "LGT Young Soloists - Polonais de Concert, Op. 14 (Arr. for Cello and String Orchestra)"
  },
  {
    "preview_url": "https://p.scdn.co/mp3-preview/e637404200f56b7474dee09da40c84e566e4d947",
    "preview_title": "Beckendorff Junior High String Orchestra - Warrior Legacy"
  },
  {
    "preview_url": "https://p.scdn.co/mp3-preview/16f37e36a7c76264d05e576beb351a35e1d4126d",
    "preview_title": "LSO String Ensemble - Variations on a Theme of Frank Bridge, Op. 10: Var. VIII. Funeral March"
  },
  {
    "preview_url": "https://p.scdn.co/mp3-preview/757837307e56b6b5cf0942e55c4b4a05b8b046a0",
    "preview_title": "Deutsche Streicherphilharmonie - Palladio: I. Allegretto"
  },
  {
    "preview_url": "https://p.scdn.co/mp3-preview/91d887a8fc6dbf689604686cd98b85f834a942fb",
    "preview_title": "String Orchestra of Brooklyn - With Eyes the Color of Time: I. The Bronze Doors"
  },
  {
    "preview_url": "https://p.scdn.co/mp3-preview/20be7bc6764684b73cc2d55c2aafbd90d958b098",
    "preview_title": "Boyd Neel String Orchestra - Brandenburg Concerto No. 6 in B-Flat Major, BWV 1051: 2. Adagio ma non tanto"
  },
  {
    "preview_url": "https://p.scdn.co/mp3-preview/88815d3d853ce4625b1ce67c68a9a74566d587cf",
    "preview_title": "Oslo Camerata - Fra Holbergs tid (From Holberg's Time), Op. 40 (version for orchestra): III. Gavotte: Allegretto - Musette: Poco piu mosso"
  },
  {
    "preview_url": "https://p.scdn.co/mp3-preview/8e7261b6625f15d19d18e5be4c127ede991fe06c",
    "preview_title": "Texas All-State String Orchestra - Molly on the Shore"
  },
  {
    "preview_url": "https://p.scdn.co/mp3-preview/f179455d798e362268412d4ef19509d38c9d31df",
    "preview_title": "Georgisches Kammerorchester Ingolstadt - Partita for String Orchestra, H. 212 \"Suite No. 1\": I. Poco allegro"
  },
  {
    "preview_url": "https://p.scdn.co/mp3-preview/3bda05dba685a6065e8a806680bf244f46df15b4",
    "preview_title": "Prague Festival Strings - Concerto for 2 Violins in A Minor, Op. 3, No. 8, RV 522: II. Larghetto e spirituoso"
  },
  {
    "preview_url": "https://p.scdn.co/mp3-preview/fbcac33fc949c7cf9af16c8627f4fea125eaa3b5",
    "preview_title": "Thirteen Strings Chamber Orchestra - Symphony in G Major, Op. 2 No. 5, Callen 11: I. Allegro assai"
  },
  {
    "preview_url": "https://p.scdn.co/mp3-preview/3cf4cf751d2c6f0b21018fd4f18549b2d06991dd",
    "preview_title": "Russian String Orchestra - Symphony for Strings, \"...For Love Is Strong as Death...\": I. Moderato e triste - Agitato"
  },
  {
    "preview_url": "https://p.scdn.co/mp3-preview/38adc884f53aded92cf19740363a7a30f9bd9c0e",
    "preview_title": "Boho Strings - Four Pieces: I. Furioso"
  },
  {
    "preview_url": "https://p.scdn.co/mp3-preview/c0d3494674fdfd6fbcc5da19e4299221ea11d83c",
    "preview_title": "SONYC - Visions and Miracles: I add brilliance to the sun"
  },
  {
    "preview_url": "https://p.scdn.co/mp3-preview/2e1afbafc5be98f85faeef109353046d77aebfe8",
    "preview_title": "New European Strings Chamber Orchestra - 2 Pieces for String Octet, Op. 11: I. Prelude: Adagio - Piu mosso"
  },
  {
    "preview_url": "https://p.scdn.co/mp3-preview/aaa8620566cc6ba13e879d03ce8008c6b686a783",
    "preview_title": "Dalgat String Ensemble - Sinfonietta in A Minor, Op. 68, No. 2: I. Allegro molto - Andante"
  },
  {
    "preview_url": "https://p.scdn.co/mp3-preview/6e0848ac055d11955ea29ce9a219f0c7e607b870",
    "preview_title": "The Strings of the Philadelphia Orchestra - Eine Kleine Nachtmusik (Serenade In G Major, K.525): I. Allegro"
  },
  {
    "preview_url": "https://p.scdn.co/mp3-preview/74affb70bbd5164dd07097dfe386d1a2ba25a095",
    "preview_title": "Ensemble Neue Streicher - Pantalon und Columbine (after W.A. Mozart): Scene 7 (from K. 446)"
  }
]